{"semana": "2022-12-26/2023-01-01", "n_cuencas": 549, "resultados": [{"hybas_id": 6100104690, "probabilidad_deslizamiento": 0.868, "nivel_riesgo": "Alto", "timestamp": "2026-05-20T04:05:55.914632+00:00"}, {"hybas_id": 6100997810, "probabilidad_deslizamiento": 0.6679, "nivel_riesgo": "Alto", "timestamp": "2026-05-20T04:05:55.914632+00:00"}, {"hybas_id": 6100102970, "probabilidad_deslizamiento": 0.6727, "nivel_riesgo": "Alto", "timestamp": "2026-05-20T04:05:55.914632+00:00"}, {"hybas_id": 6100101980, "probabilidad_deslizamiento": 0.6809, "nivel_riesgo": "Alto", "timestamp": "2026-05-20T04:05:55.914632+00:00"}, {"hybas_id": 6100101810, "probabilidad_deslizamiento": 0.8407, "nivel_riesgo": "Alto", "timestamp": "2026-05-20T04:05:55.914632+00:00"}, {"hybas_id": 6100101900, "probabilidad_deslizamiento": 0.78, "nivel_riesgo": "Alto", "timestamp": "2026-05-20T04:05:55.914632+00:00"}, {"hybas_id": 6100104620, "probabilidad_deslizamiento": 0.8725, "nivel_riesgo": "Alto", "timestamp": "2026-05-20T04:05:55.914632+00:00"}, {"hybas_id": 6100997740, "probabilidad_deslizamiento": 0.0207, "nivel_riesgo": "Bajo", "timestamp": "2026-05-20T04:05:55.914632+00:00"}, {"hybas_id": 6100101610, "probabilidad_deslizamiento": 0.868, "nivel_riesgo": "Alto", "timestamp": "2026-05-20T04:05:55.914632+00:00"}, {"hybas_id": 6100101540, "probabilidad_deslizamiento": 0.0227, "nivel_riesgo": "Bajo", "timestamp": "2026-05-20T04:05:55.914632+00:00"}, {"hybas_id": 6100099730, "probabilidad_deslizamiento": 0.8716, "nivel_riesgo": "Alto", "timestamp": "2026-05-20T04:05:55.914632+00:00"}, {"hybas_id": 6100098900, "probabilidad_deslizamiento": 0.0222, "nivel_riesgo": "Bajo", "timestamp": "2026-05-20T04:05:55.914632+00:00"}, {"hybas_id": 6100098410, "probabilidad_deslizamiento": 0.0213, "nivel_riesgo": "Bajo", "timestamp": "2026-05-20T04:05:55.914632+00:00"}, {"hybas_id": 6100098850, "probabilidad_deslizamiento": 0.681, "nivel_riesgo": "Alto", "timestamp": "2026-05-20T04:05:55.914632+00:00"}, {"hybas_id": 6100097280, "probabilidad_deslizamiento": 0.6816, "nivel_riesgo": "Alto", "timestamp": "2026-05-20T04:05:55.914632+00:00"}, {"hybas_id": 6100097200, "probabilidad_deslizamiento": 0.6816, "nivel_riesgo": "Alto", "timestamp": "2026-05-20T04:05:55.914632+00:00"}, {"hybas_id": 6100101820, "probabilidad_deslizamiento": 0.6828, "nivel_riesgo": "Alto", "timestamp": "2026-05-20T04:05:55.914632+00:00"}, {"hybas_id": 6100100130, "probabilidad_deslizamiento": 0.8711, "nivel_riesgo": "Alto", "timestamp": "2026-05-20T04:05:55.914632+00:00"}, {"hybas_id": 6100100180, "probabilidad_deslizamiento": 0.0204, "nivel_riesgo": "Bajo", "timestamp": "2026-05-20T04:05:55.914632+00:00"}, {"hybas_id": 6100099820, "probabilidad_deslizamiento": 0.6828, "nivel_riesgo": "Alto", "timestamp": "2026-05-20T04:05:55.914632+00:00"}, {"hybas_id": 6100099720, "probabilidad_deslizamiento": 0.8701, "nivel_riesgo": "Alto", "timestamp": "2026-05-20T04:05:55.914632+00:00"}, {"hybas_id": 6100099410, "probabilidad_deslizamiento": 0.6823, "nivel_riesgo": "Alto", "timestamp": "2026-05-20T04:05:55.914632+00:00"}, {"hybas_id": 6100099180, "probabilidad_deslizamiento": 0.6823, "nivel_riesgo": "Alto", "timestamp": "2026-05-20T04:05:55.914632+00:00"}, {"hybas_id": 6100099130, "probabilidad_deslizamiento": 0.0192, "nivel_riesgo": "Bajo", "timestamp": "2026-05-20T04:05:55.914632+00:00"}, {"hybas_id": 6100097540, "probabilidad_deslizamiento": 0.8749, "nivel_riesgo": "Alto", "timestamp": "2026-05-20T04:05:55.914632+00:00"}, {"hybas_id": 6100115670, "probabilidad_deslizamiento": 0.8782, "nivel_riesgo": "Alto", "timestamp": "2026-05-20T04:05:55.914632+00:00"}, {"hybas_id": 6100113400, "probabilidad_deslizamiento": 0.8732, "nivel_riesgo": "Alto", "timestamp": "2026-05-20T04:05:55.914632+00:00"}, {"hybas_id": 6100110930, "probabilidad_deslizamiento": 0.7007, "nivel_riesgo": "Alto", "timestamp": "2026-05-20T04:05:55.914632+00:00"}, {"hybas_id": 6100109880, "probabilidad_deslizamiento": 0.0433, "nivel_riesgo": "Bajo", "timestamp": "2026-05-20T04:05:55.914632+00:00"}, {"hybas_id": 6100108570, "probabilidad_deslizamiento": 0.0406, "nivel_riesgo": "Bajo", "timestamp": "2026-05-20T04:05:55.914632+00:00"}, {"hybas_id": 6100107990, "probabilidad_deslizamiento": 0.8263, "nivel_riesgo": "Alto", "timestamp": "2026-05-20T04:05:55.914632+00:00"}, {"hybas_id": 6100108530, "probabilidad_deslizamiento": 0.0383, "nivel_riesgo": "Bajo", "timestamp": "2026-05-20T04:05:55.914632+00:00"}, {"hybas_id": 6101002540, "probabilidad_deslizamiento": 0.7506, "nivel_riesgo": "Alto", "timestamp": "2026-05-20T04:05:55.914632+00:00"}, {"hybas_id": 6100113590, "probabilidad_deslizamiento": 0.868, "nivel_riesgo": "Alto", "timestamp": "2026-05-20T04:05:55.914632+00:00"}, {"hybas_id": 6100109970, "probabilidad_deslizamiento": 0.0406, "nivel_riesgo": "Bajo", "timestamp": "2026-05-20T04:05:55.914632+00:00"}, {"hybas_id": 6101001740, "probabilidad_deslizamiento": 0.8335, "nivel_riesgo": "Alto", "timestamp": "2026-05-20T04:05:55.914632+00:00"}, {"hybas_id": 6101001330, "probabilidad_deslizamiento": 0.0217, "nivel_riesgo": "Bajo", "timestamp": "2026-05-20T04:05:55.914632+00:00"}, {"hybas_id": 6100108370, "probabilidad_deslizamiento": 0.8837, "nivel_riesgo": "Alto", "timestamp": "2026-05-20T04:05:55.914632+00:00"}, {"hybas_id": 6100108320, "probabilidad_deslizamiento": 0.0378, "nivel_riesgo": "Bajo", "timestamp": "2026-05-20T04:05:55.914632+00:00"}, {"hybas_id": 6101001570, "probabilidad_deslizamiento": 0.0474, "nivel_riesgo": "Bajo", "timestamp": "2026-05-20T04:05:55.914632+00:00"}, {"hybas_id": 6101001140, "probabilidad_deslizamiento": 0.6815, "nivel_riesgo": "Alto", "timestamp": "2026-05-20T04:05:55.914632+00:00"}, {"hybas_id": 6101000660, "probabilidad_deslizamiento": 0.6973, "nivel_riesgo": "Alto", "timestamp": "2026-05-20T04:05:55.914632+00:00"}, {"hybas_id": 6100108150, "probabilidad_deslizamiento": 0.8842, "nivel_riesgo": "Alto", "timestamp": "2026-05-20T04:05:55.914632+00:00"}, {"hybas_id": 6100108540, "probabilidad_deslizamiento": 0.6997, "nivel_riesgo": "Alto", "timestamp": "2026-05-20T04:05:55.914632+00:00"}, {"hybas_id": 6100108440, "probabilidad_deslizamiento": 0.8782, "nivel_riesgo": "Alto", "timestamp": "2026-05-20T04:05:55.914632+00:00"}, {"hybas_id": 6100107870, "probabilidad_deslizamiento": 0.7029, "nivel_riesgo": "Alto", "timestamp": "2026-05-20T04:05:55.914632+00:00"}, {"hybas_id": 6100107440, "probabilidad_deslizamiento": 0.6799, "nivel_riesgo": "Alto", "timestamp": "2026-05-20T04:05:55.914632+00:00"}, {"hybas_id": 6100107720, "probabilidad_deslizamiento": 0.7022, "nivel_riesgo": "Alto", "timestamp": "2026-05-20T04:05:55.914632+00:00"}, {"hybas_id": 6100106650, "probabilidad_deslizamiento": 0.0382, "nivel_riesgo": "Bajo", "timestamp": "2026-05-20T04:05:55.914632+00:00"}, {"hybas_id": 6100107450, "probabilidad_deslizamiento": 0.7015, "nivel_riesgo": "Alto", "timestamp": "2026-05-20T04:05:55.914632+00:00"}, {"hybas_id": 6100106660, "probabilidad_deslizamiento": 0.7007, "nivel_riesgo": "Alto", "timestamp": "2026-05-20T04:05:55.914632+00:00"}, {"hybas_id": 6100105430, "probabilidad_deslizamiento": 0.6993, "nivel_riesgo": "Alto", "timestamp": "2026-05-20T04:05:55.914632+00:00"}, {"hybas_id": 6100999210, "probabilidad_deslizamiento": 0.6993, "nivel_riesgo": "Alto", "timestamp": "2026-05-20T04:05:55.914632+00:00"}, {"hybas_id": 6100107550, "probabilidad_deslizamiento": 0.6665, "nivel_riesgo": "Alto", "timestamp": "2026-05-20T04:05:55.914632+00:00"}, {"hybas_id": 6100104630, "probabilidad_deslizamiento": 0.8058, "nivel_riesgo": "Alto", "timestamp": "2026-05-20T04:05:55.914632+00:00"}, {"hybas_id": 6101000200, "probabilidad_deslizamiento": 0.0205, "nivel_riesgo": "Bajo", "timestamp": "2026-05-20T04:05:55.914632+00:00"}, {"hybas_id": 6100106470, "probabilidad_deslizamiento": 0.8843, "nivel_riesgo": "Alto", "timestamp": "2026-05-20T04:05:55.914632+00:00"}, {"hybas_id": 6100106510, "probabilidad_deslizamiento": 0.6786, "nivel_riesgo": "Alto", "timestamp": "2026-05-20T04:05:55.914632+00:00"}, {"hybas_id": 6100999670, "probabilidad_deslizamiento": 0.789, "nivel_riesgo": "Alto", "timestamp": "2026-05-20T04:05:55.914632+00:00"}, {"hybas_id": 6100105920, "probabilidad_deslizamiento": 0.7028, "nivel_riesgo": "Alto", "timestamp": "2026-05-20T04:05:55.914632+00:00"}, {"hybas_id": 6100105420, "probabilidad_deslizamiento": 0.7028, "nivel_riesgo": "Alto", "timestamp": "2026-05-20T04:05:55.914632+00:00"}, {"hybas_id": 6100999340, "probabilidad_deslizamiento": 0.0218, "nivel_riesgo": "Bajo", "timestamp": "2026-05-20T04:05:55.914632+00:00"}, {"hybas_id": 6100105890, "probabilidad_deslizamiento": 0.8807, "nivel_riesgo": "Alto", "timestamp": "2026-05-20T04:05:55.914632+00:00"}, {"hybas_id": 6100104700, "probabilidad_deslizamiento": 0.7001, "nivel_riesgo": "Alto", "timestamp": "2026-05-20T04:05:55.914632+00:00"}, {"hybas_id": 6100108000, "probabilidad_deslizamiento": 0.8831, "nivel_riesgo": "Alto", "timestamp": "2026-05-20T04:05:55.914632+00:00"}, {"hybas_id": 6100105530, "probabilidad_deslizamiento": 0.0412, "nivel_riesgo": "Bajo", "timestamp": "2026-05-20T04:05:55.914632+00:00"}, {"hybas_id": 6100105440, "probabilidad_deslizamiento": 0.679, "nivel_riesgo": "Alto", "timestamp": "2026-05-20T04:05:55.914632+00:00"}, {"hybas_id": 6100105490, "probabilidad_deslizamiento": 0.0409, "nivel_riesgo": "Bajo", "timestamp": "2026-05-20T04:05:55.914632+00:00"}, {"hybas_id": 6100105480, "probabilidad_deslizamiento": 0.0372, "nivel_riesgo": "Bajo", "timestamp": "2026-05-20T04:05:55.914632+00:00"}, {"hybas_id": 6100102880, "probabilidad_deslizamiento": 0.0725, "nivel_riesgo": "Bajo", "timestamp": "2026-05-20T04:05:55.914632+00:00"}, {"hybas_id": 6100997940, "probabilidad_deslizamiento": 0.0878, "nivel_riesgo": "Bajo", "timestamp": "2026-05-20T04:05:55.914632+00:00"}, {"hybas_id": 6100102520, "probabilidad_deslizamiento": 0.6961, "nivel_riesgo": "Alto", "timestamp": "2026-05-20T04:05:55.914632+00:00"}, {"hybas_id": 6100102870, "probabilidad_deslizamiento": 0.6786, "nivel_riesgo": "Alto", "timestamp": "2026-05-20T04:05:55.914632+00:00"}, {"hybas_id": 6100997110, "probabilidad_deslizamiento": 0.6948, "nivel_riesgo": "Alto", "timestamp": "2026-05-20T04:05:55.914632+00:00"}, {"hybas_id": 6100103540, "probabilidad_deslizamiento": 0.7008, "nivel_riesgo": "Alto", "timestamp": "2026-05-20T04:05:55.914632+00:00"}, {"hybas_id": 6100997680, "probabilidad_deslizamiento": 0.0192, "nivel_riesgo": "Bajo", "timestamp": "2026-05-20T04:05:55.914632+00:00"}, {"hybas_id": 6100101920, "probabilidad_deslizamiento": 0.8687, "nivel_riesgo": "Alto", "timestamp": "2026-05-20T04:05:55.914632+00:00"}, {"hybas_id": 6100101460, "probabilidad_deslizamiento": 0.8704, "nivel_riesgo": "Alto", "timestamp": "2026-05-20T04:05:55.914632+00:00"}, {"hybas_id": 6100101910, "probabilidad_deslizamiento": 0.8813, "nivel_riesgo": "Alto", "timestamp": "2026-05-20T04:05:55.914632+00:00"}, {"hybas_id": 6100101450, "probabilidad_deslizamiento": 0.6565, "nivel_riesgo": "Alto", "timestamp": "2026-05-20T04:05:55.914632+00:00"}, {"hybas_id": 6100101500, "probabilidad_deslizamiento": 0.7027, "nivel_riesgo": "Alto", "timestamp": "2026-05-20T04:05:55.914632+00:00"}, {"hybas_id": 6100100410, "probabilidad_deslizamiento": 0.6746, "nivel_riesgo": "Alto", "timestamp": "2026-05-20T04:05:55.914632+00:00"}, {"hybas_id": 6100996830, "probabilidad_deslizamiento": 0.8682, "nivel_riesgo": "Alto", "timestamp": "2026-05-20T04:05:55.914632+00:00"}, {"hybas_id": 6100099740, "probabilidad_deslizamiento": 0.7017, "nivel_riesgo": "Alto", "timestamp": "2026-05-20T04:05:55.914632+00:00"}, {"hybas_id": 6100997560, "probabilidad_deslizamiento": 0.0419, "nivel_riesgo": "Bajo", "timestamp": "2026-05-20T04:05:55.914632+00:00"}, {"hybas_id": 6100997930, "probabilidad_deslizamiento": 0.0446, "nivel_riesgo": "Bajo", "timestamp": "2026-05-20T04:05:55.914632+00:00"}, {"hybas_id": 6100103490, "probabilidad_deslizamiento": 0.6801, "nivel_riesgo": "Alto", "timestamp": "2026-05-20T04:05:55.914632+00:00"}, {"hybas_id": 6100997340, "probabilidad_deslizamiento": 0.6812, "nivel_riesgo": "Alto", "timestamp": "2026-05-20T04:05:55.914632+00:00"}, {"hybas_id": 6100101510, "probabilidad_deslizamiento": 0.0436, "nivel_riesgo": "Bajo", "timestamp": "2026-05-20T04:05:55.914632+00:00"}, {"hybas_id": 6100997000, "probabilidad_deslizamiento": 0.6947, "nivel_riesgo": "Alto", "timestamp": "2026-05-20T04:05:55.914632+00:00"}, {"hybas_id": 6100996770, "probabilidad_deslizamiento": 0.7073, "nivel_riesgo": "Alto", "timestamp": "2026-05-20T04:05:55.914632+00:00"}, {"hybas_id": 6100996620, "probabilidad_deslizamiento": 0.7103, "nivel_riesgo": "Alto", "timestamp": "2026-05-20T04:05:55.914632+00:00"}, {"hybas_id": 6100098450, "probabilidad_deslizamiento": 0.8815, "nivel_riesgo": "Alto", "timestamp": "2026-05-20T04:05:55.914632+00:00"}, {"hybas_id": 6100098110, "probabilidad_deslizamiento": 0.8812, "nivel_riesgo": "Alto", "timestamp": "2026-05-20T04:05:55.914632+00:00"}, {"hybas_id": 6100100360, "probabilidad_deslizamiento": 0.0213, "nivel_riesgo": "Bajo", "timestamp": "2026-05-20T04:05:55.914632+00:00"}, {"hybas_id": 6100099560, "probabilidad_deslizamiento": 0.8813, "nivel_riesgo": "Alto", "timestamp": "2026-05-20T04:05:55.914632+00:00"}, {"hybas_id": 6100098530, "probabilidad_deslizamiento": 0.7022, "nivel_riesgo": "Alto", "timestamp": "2026-05-20T04:05:55.914632+00:00"}, {"hybas_id": 6100099640, "probabilidad_deslizamiento": 0.8698, "nivel_riesgo": "Alto", "timestamp": "2026-05-20T04:05:55.914632+00:00"}, {"hybas_id": 6100098050, "probabilidad_deslizamiento": 0.6964, "nivel_riesgo": "Alto", "timestamp": "2026-05-20T04:05:55.914632+00:00"}, {"hybas_id": 6100097410, "probabilidad_deslizamiento": 0.0375, "nivel_riesgo": "Bajo", "timestamp": "2026-05-20T04:05:55.914632+00:00"}, {"hybas_id": 6100994880, "probabilidad_deslizamiento": 0.0217, "nivel_riesgo": "Bajo", "timestamp": "2026-05-20T04:05:55.914632+00:00"}, {"hybas_id": 6100097360, "probabilidad_deslizamiento": 0.7839, "nivel_riesgo": "Alto", "timestamp": "2026-05-20T04:05:55.914632+00:00"}, {"hybas_id": 6100994380, "probabilidad_deslizamiento": 0.6566, "nivel_riesgo": "Alto", "timestamp": "2026-05-20T04:05:55.914632+00:00"}, {"hybas_id": 6100994070, "probabilidad_deslizamiento": 0.0225, "nivel_riesgo": "Bajo", "timestamp": "2026-05-20T04:05:55.914632+00:00"}, {"hybas_id": 6100098160, "probabilidad_deslizamiento": 0.7026, "nivel_riesgo": "Alto", "timestamp": "2026-05-20T04:05:55.914632+00:00"}, {"hybas_id": 6100098100, "probabilidad_deslizamiento": 0.7026, "nivel_riesgo": "Alto", "timestamp": "2026-05-20T04:05:55.914632+00:00"}, {"hybas_id": 6100097950, "probabilidad_deslizamiento": 0.7031, "nivel_riesgo": "Alto", "timestamp": "2026-05-20T04:05:55.914632+00:00"}, {"hybas_id": 6100995750, "probabilidad_deslizamiento": 0.8827, "nivel_riesgo": "Alto", "timestamp": "2026-05-20T04:05:55.914632+00:00"}, {"hybas_id": 6100097960, "probabilidad_deslizamiento": 0.039, "nivel_riesgo": "Bajo", "timestamp": "2026-05-20T04:05:55.914632+00:00"}, {"hybas_id": 6100096590, "probabilidad_deslizamiento": 0.8083, "nivel_riesgo": "Alto", "timestamp": "2026-05-20T04:05:55.914632+00:00"}, {"hybas_id": 6100995040, "probabilidad_deslizamiento": 0.7483, "nivel_riesgo": "Alto", "timestamp": "2026-05-20T04:05:55.914632+00:00"}, {"hybas_id": 6100095120, "probabilidad_deslizamiento": 0.6814, "nivel_riesgo": "Alto", "timestamp": "2026-05-20T04:05:55.914632+00:00"}, {"hybas_id": 6100096300, "probabilidad_deslizamiento": 0.0393, "nivel_riesgo": "Bajo", "timestamp": "2026-05-20T04:05:55.914632+00:00"}, {"hybas_id": 6100096530, "probabilidad_deslizamiento": 0.0457, "nivel_riesgo": "Bajo", "timestamp": "2026-05-20T04:05:55.914632+00:00"}, {"hybas_id": 6100097270, "probabilidad_deslizamiento": 0.6822, "nivel_riesgo": "Alto", "timestamp": "2026-05-20T04:05:55.914632+00:00"}, {"hybas_id": 6100096570, "probabilidad_deslizamiento": 0.0204, "nivel_riesgo": "Bajo", "timestamp": "2026-05-20T04:05:55.914632+00:00"}, {"hybas_id": 6100096440, "probabilidad_deslizamiento": 0.6691, "nivel_riesgo": "Alto", "timestamp": "2026-05-20T04:05:55.914632+00:00"}, {"hybas_id": 6100096470, "probabilidad_deslizamiento": 0.6829, "nivel_riesgo": "Alto", "timestamp": "2026-05-20T04:05:55.914632+00:00"}, {"hybas_id": 6100096580, "probabilidad_deslizamiento": 0.8415, "nivel_riesgo": "Alto", "timestamp": "2026-05-20T04:05:55.914632+00:00"}, {"hybas_id": 6100098370, "probabilidad_deslizamiento": 0.6821, "nivel_riesgo": "Alto", "timestamp": "2026-05-20T04:05:55.914632+00:00"}, {"hybas_id": 6100097940, "probabilidad_deslizamiento": 0.0197, "nivel_riesgo": "Bajo", "timestamp": "2026-05-20T04:05:55.914632+00:00"}, {"hybas_id": 6100097860, "probabilidad_deslizamiento": 0.0194, "nivel_riesgo": "Bajo", "timestamp": "2026-05-20T04:05:55.914632+00:00"}, {"hybas_id": 6100097170, "probabilidad_deslizamiento": 0.6593, "nivel_riesgo": "Alto", "timestamp": "2026-05-20T04:05:55.914632+00:00"}, {"hybas_id": 6100097210, "probabilidad_deslizamiento": 0.6796, "nivel_riesgo": "Alto", "timestamp": "2026-05-20T04:05:55.914632+00:00"}, {"hybas_id": 6100097150, "probabilidad_deslizamiento": 0.6756, "nivel_riesgo": "Alto", "timestamp": "2026-05-20T04:05:55.914632+00:00"}, {"hybas_id": 6100096290, "probabilidad_deslizamiento": 0.8662, "nivel_riesgo": "Alto", "timestamp": "2026-05-20T04:05:55.914632+00:00"}, {"hybas_id": 6100097140, "probabilidad_deslizamiento": 0.872, "nivel_riesgo": "Alto", "timestamp": "2026-05-20T04:05:55.914632+00:00"}, {"hybas_id": 6100096230, "probabilidad_deslizamiento": 0.8627, "nivel_riesgo": "Alto", "timestamp": "2026-05-20T04:05:55.914632+00:00"}, {"hybas_id": 6100093290, "probabilidad_deslizamiento": 0.8748, "nivel_riesgo": "Alto", "timestamp": "2026-05-20T04:05:55.914632+00:00"}, {"hybas_id": 6100097090, "probabilidad_deslizamiento": 0.0203, "nivel_riesgo": "Bajo", "timestamp": "2026-05-20T04:05:55.914632+00:00"}, {"hybas_id": 6100097050, "probabilidad_deslizamiento": 0.8408, "nivel_riesgo": "Alto", "timestamp": "2026-05-20T04:05:55.914632+00:00"}, {"hybas_id": 6100097490, "probabilidad_deslizamiento": 0.6817, "nivel_riesgo": "Alto", "timestamp": "2026-05-20T04:05:55.914632+00:00"}, {"hybas_id": 6100093560, "probabilidad_deslizamiento": 0.8752, "nivel_riesgo": "Alto", "timestamp": "2026-05-20T04:05:55.914632+00:00"}, {"hybas_id": 6100093480, "probabilidad_deslizamiento": 0.8734, "nivel_riesgo": "Alto", "timestamp": "2026-05-20T04:05:55.914632+00:00"}, {"hybas_id": 6100993160, "probabilidad_deslizamiento": 0.0228, "nivel_riesgo": "Bajo", "timestamp": "2026-05-20T04:05:55.914632+00:00"}, {"hybas_id": 6100091910, "probabilidad_deslizamiento": 0.6782, "nivel_riesgo": "Alto", "timestamp": "2026-05-20T04:05:55.914632+00:00"}, {"hybas_id": 6100091540, "probabilidad_deslizamiento": 0.6595, "nivel_riesgo": "Alto", "timestamp": "2026-05-20T04:05:55.914632+00:00"}, {"hybas_id": 6100992160, "probabilidad_deslizamiento": 0.8686, "nivel_riesgo": "Alto", "timestamp": "2026-05-20T04:05:55.914632+00:00"}, {"hybas_id": 6100091010, "probabilidad_deslizamiento": 0.0202, "nivel_riesgo": "Bajo", "timestamp": "2026-05-20T04:05:55.914632+00:00"}, {"hybas_id": 6100094710, "probabilidad_deslizamiento": 0.6809, "nivel_riesgo": "Alto", "timestamp": "2026-05-20T04:05:55.914632+00:00"}, {"hybas_id": 6100092610, "probabilidad_deslizamiento": 0.8738, "nivel_riesgo": "Alto", "timestamp": "2026-05-20T04:05:55.914632+00:00"}, {"hybas_id": 6100092620, "probabilidad_deslizamiento": 0.8753, "nivel_riesgo": "Alto", "timestamp": "2026-05-20T04:05:55.914632+00:00"}, {"hybas_id": 6100092570, "probabilidad_deslizamiento": 0.875, "nivel_riesgo": "Alto", "timestamp": "2026-05-20T04:05:55.914632+00:00"}, {"hybas_id": 6100092360, "probabilidad_deslizamiento": 0.6817, "nivel_riesgo": "Alto", "timestamp": "2026-05-20T04:05:55.914632+00:00"}, {"hybas_id": 6100091200, "probabilidad_deslizamiento": 0.6756, "nivel_riesgo": "Alto", "timestamp": "2026-05-20T04:05:55.914632+00:00"}, {"hybas_id": 6100992860, "probabilidad_deslizamiento": 0.6835, "nivel_riesgo": "Alto", "timestamp": "2026-05-20T04:05:55.914632+00:00"}, {"hybas_id": 6100091210, "probabilidad_deslizamiento": 0.6813, "nivel_riesgo": "Alto", "timestamp": "2026-05-20T04:05:55.914632+00:00"}, {"hybas_id": 6100092270, "probabilidad_deslizamiento": 0.8753, "nivel_riesgo": "Alto", "timestamp": "2026-05-20T04:05:55.914632+00:00"}, {"hybas_id": 6100089880, "probabilidad_deslizamiento": 0.8434, "nivel_riesgo": "Alto", "timestamp": "2026-05-20T04:05:55.914632+00:00"}, {"hybas_id": 6100089820, "probabilidad_deslizamiento": 0.0202, "nivel_riesgo": "Bajo", "timestamp": "2026-05-20T04:05:55.914632+00:00"}, {"hybas_id": 6100089420, "probabilidad_deslizamiento": 0.681, "nivel_riesgo": "Alto", "timestamp": "2026-05-20T04:05:55.914632+00:00"}, {"hybas_id": 6100088240, "probabilidad_deslizamiento": 0.5882, "nivel_riesgo": "Medio", "timestamp": "2026-05-20T04:05:55.914632+00:00"}, {"hybas_id": 6100088090, "probabilidad_deslizamiento": 0.0228, "nivel_riesgo": "Bajo", "timestamp": "2026-05-20T04:05:55.914632+00:00"}, {"hybas_id": 6100088150, "probabilidad_deslizamiento": 0.6817, "nivel_riesgo": "Alto", "timestamp": "2026-05-20T04:05:55.914632+00:00"}, {"hybas_id": 6100088100, "probabilidad_deslizamiento": 0.681, "nivel_riesgo": "Alto", "timestamp": "2026-05-20T04:05:55.914632+00:00"}, {"hybas_id": 6100991090, "probabilidad_deslizamiento": 0.6815, "nivel_riesgo": "Alto", "timestamp": "2026-05-20T04:05:55.914632+00:00"}, {"hybas_id": 6100990970, "probabilidad_deslizamiento": 0.6803, "nivel_riesgo": "Alto", "timestamp": "2026-05-20T04:05:55.914632+00:00"}, {"hybas_id": 6100086490, "probabilidad_deslizamiento": 0.6565, "nivel_riesgo": "Alto", "timestamp": "2026-05-20T04:05:55.914632+00:00"}, {"hybas_id": 6100088560, "probabilidad_deslizamiento": 0.0209, "nivel_riesgo": "Bajo", "timestamp": "2026-05-20T04:05:55.914632+00:00"}, {"hybas_id": 6100089340, "probabilidad_deslizamiento": 0.0217, "nivel_riesgo": "Bajo", "timestamp": "2026-05-20T04:05:55.914632+00:00"}, {"hybas_id": 6100088160, "probabilidad_deslizamiento": 0.8732, "nivel_riesgo": "Alto", "timestamp": "2026-05-20T04:05:55.914632+00:00"}, {"hybas_id": 6100990620, "probabilidad_deslizamiento": 0.0217, "nivel_riesgo": "Bajo", "timestamp": "2026-05-20T04:05:55.914632+00:00"}, {"hybas_id": 6100088110, "probabilidad_deslizamiento": 0.0203, "nivel_riesgo": "Bajo", "timestamp": "2026-05-20T04:05:55.914632+00:00"}, {"hybas_id": 6100990690, "probabilidad_deslizamiento": 0.0212, "nivel_riesgo": "Bajo", "timestamp": "2026-05-20T04:05:55.914632+00:00"}, {"hybas_id": 6100989940, "probabilidad_deslizamiento": 0.8669, "nivel_riesgo": "Alto", "timestamp": "2026-05-20T04:05:55.914632+00:00"}, {"hybas_id": 6100989930, "probabilidad_deslizamiento": 0.6714, "nivel_riesgo": "Alto", "timestamp": "2026-05-20T04:05:55.914632+00:00"}, {"hybas_id": 6100989260, "probabilidad_deslizamiento": 0.0202, "nivel_riesgo": "Bajo", "timestamp": "2026-05-20T04:05:55.914632+00:00"}, {"hybas_id": 6100988770, "probabilidad_deslizamiento": 0.6559, "nivel_riesgo": "Alto", "timestamp": "2026-05-20T04:05:55.914632+00:00"}, {"hybas_id": 6100098060, "probabilidad_deslizamiento": 0.7019, "nivel_riesgo": "Alto", "timestamp": "2026-05-20T04:05:55.914632+00:00"}, {"hybas_id": 6100994850, "probabilidad_deslizamiento": 0.0244, "nivel_riesgo": "Bajo", "timestamp": "2026-05-20T04:05:55.914632+00:00"}, {"hybas_id": 6100994400, "probabilidad_deslizamiento": 0.658, "nivel_riesgo": "Alto", "timestamp": "2026-05-20T04:05:55.914632+00:00"}, {"hybas_id": 6100993900, "probabilidad_deslizamiento": 0.8645, "nivel_riesgo": "Alto", "timestamp": "2026-05-20T04:05:55.914632+00:00"}, {"hybas_id": 6100096240, "probabilidad_deslizamiento": 0.0417, "nivel_riesgo": "Bajo", "timestamp": "2026-05-20T04:05:55.914632+00:00"}, {"hybas_id": 6100092760, "probabilidad_deslizamiento": 0.859, "nivel_riesgo": "Alto", "timestamp": "2026-05-20T04:05:55.914632+00:00"}, {"hybas_id": 6100092590, "probabilidad_deslizamiento": 0.6602, "nivel_riesgo": "Alto", "timestamp": "2026-05-20T04:05:55.914632+00:00"}, {"hybas_id": 6100092750, "probabilidad_deslizamiento": 0.8699, "nivel_riesgo": "Alto", "timestamp": "2026-05-20T04:05:55.914632+00:00"}, {"hybas_id": 6100092580, "probabilidad_deslizamiento": 0.6769, "nivel_riesgo": "Alto", "timestamp": "2026-05-20T04:05:55.914632+00:00"}, {"hybas_id": 6100092020, "probabilidad_deslizamiento": 0.6792, "nivel_riesgo": "Alto", "timestamp": "2026-05-20T04:05:55.914632+00:00"}, {"hybas_id": 6100094190, "probabilidad_deslizamiento": 0.6734, "nivel_riesgo": "Alto", "timestamp": "2026-05-20T04:05:55.914632+00:00"}, {"hybas_id": 6100095010, "probabilidad_deslizamiento": 0.0257, "nivel_riesgo": "Bajo", "timestamp": "2026-05-20T04:05:55.914632+00:00"}, {"hybas_id": 6100094200, "probabilidad_deslizamiento": 0.6609, "nivel_riesgo": "Alto", "timestamp": "2026-05-20T04:05:55.914632+00:00"}, {"hybas_id": 6100093490, "probabilidad_deslizamiento": 0.6746, "nivel_riesgo": "Alto", "timestamp": "2026-05-20T04:05:55.914632+00:00"}, {"hybas_id": 6100093300, "probabilidad_deslizamiento": 0.677, "nivel_riesgo": "Alto", "timestamp": "2026-05-20T04:05:55.914632+00:00"}, {"hybas_id": 6100093950, "probabilidad_deslizamiento": 0.0248, "nivel_riesgo": "Bajo", "timestamp": "2026-05-20T04:05:55.914632+00:00"}, {"hybas_id": 6100093380, "probabilidad_deslizamiento": 0.8732, "nivel_riesgo": "Alto", "timestamp": "2026-05-20T04:05:55.914632+00:00"}, {"hybas_id": 6100091600, "probabilidad_deslizamiento": 0.7352, "nivel_riesgo": "Alto", "timestamp": "2026-05-20T04:05:55.914632+00:00"}, {"hybas_id": 6100092160, "probabilidad_deslizamiento": 0.8602, "nivel_riesgo": "Alto", "timestamp": "2026-05-20T04:05:55.914632+00:00"}, {"hybas_id": 6100091470, "probabilidad_deslizamiento": 0.8656, "nivel_riesgo": "Alto", "timestamp": "2026-05-20T04:05:55.914632+00:00"}, {"hybas_id": 6100094020, "probabilidad_deslizamiento": 0.6813, "nivel_riesgo": "Alto", "timestamp": "2026-05-20T04:05:55.914632+00:00"}, {"hybas_id": 6100993480, "probabilidad_deslizamiento": 0.8607, "nivel_riesgo": "Alto", "timestamp": "2026-05-20T04:05:55.914632+00:00"}, {"hybas_id": 6100092250, "probabilidad_deslizamiento": 0.8729, "nivel_riesgo": "Alto", "timestamp": "2026-05-20T04:05:55.914632+00:00"}, {"hybas_id": 6100091220, "probabilidad_deslizamiento": 0.0253, "nivel_riesgo": "Bajo", "timestamp": "2026-05-20T04:05:55.914632+00:00"}, {"hybas_id": 6100992880, "probabilidad_deslizamiento": 0.6781, "nivel_riesgo": "Alto", "timestamp": "2026-05-20T04:05:55.914632+00:00"}, {"hybas_id": 6100091060, "probabilidad_deslizamiento": 0.6771, "nivel_riesgo": "Alto", "timestamp": "2026-05-20T04:05:55.914632+00:00"}, {"hybas_id": 6100091310, "probabilidad_deslizamiento": 0.6818, "nivel_riesgo": "Alto", "timestamp": "2026-05-20T04:05:55.914632+00:00"}, {"hybas_id": 6100090450, "probabilidad_deslizamiento": 0.6822, "nivel_riesgo": "Alto", "timestamp": "2026-05-20T04:05:55.914632+00:00"}, {"hybas_id": 6100091020, "probabilidad_deslizamiento": 0.6814, "nivel_riesgo": "Alto", "timestamp": "2026-05-20T04:05:55.914632+00:00"}, {"hybas_id": 6100089760, "probabilidad_deslizamiento": 0.682, "nivel_riesgo": "Alto", "timestamp": "2026-05-20T04:05:55.914632+00:00"}, {"hybas_id": 6100992380, "probabilidad_deslizamiento": 0.869, "nivel_riesgo": "Alto", "timestamp": "2026-05-20T04:05:55.914632+00:00"}, {"hybas_id": 6100091030, "probabilidad_deslizamiento": 0.0206, "nivel_riesgo": "Bajo", "timestamp": "2026-05-20T04:05:55.914632+00:00"}, {"hybas_id": 6100089720, "probabilidad_deslizamiento": 0.0228, "nivel_riesgo": "Bajo", "timestamp": "2026-05-20T04:05:55.914632+00:00"}, {"hybas_id": 6100089730, "probabilidad_deslizamiento": 0.6839, "nivel_riesgo": "Alto", "timestamp": "2026-05-20T04:05:55.914632+00:00"}, {"hybas_id": 6100089110, "probabilidad_deslizamiento": 0.6719, "nivel_riesgo": "Alto", "timestamp": "2026-05-20T04:05:55.914632+00:00"}, {"hybas_id": 6100088720, "probabilidad_deslizamiento": 0.0214, "nivel_riesgo": "Bajo", "timestamp": "2026-05-20T04:05:55.914632+00:00"}, {"hybas_id": 6100089040, "probabilidad_deslizamiento": 0.6843, "nivel_riesgo": "Alto", "timestamp": "2026-05-20T04:05:55.914632+00:00"}, {"hybas_id": 6100089080, "probabilidad_deslizamiento": 0.6827, "nivel_riesgo": "Alto", "timestamp": "2026-05-20T04:05:55.914632+00:00"}, {"hybas_id": 6100088710, "probabilidad_deslizamiento": 0.684, "nivel_riesgo": "Alto", "timestamp": "2026-05-20T04:05:55.914632+00:00"}, {"hybas_id": 6100087940, "probabilidad_deslizamiento": 0.6831, "nivel_riesgo": "Alto", "timestamp": "2026-05-20T04:05:55.914632+00:00"}, {"hybas_id": 6100090370, "probabilidad_deslizamiento": 0.6761, "nivel_riesgo": "Alto", "timestamp": "2026-05-20T04:05:55.914632+00:00"}, {"hybas_id": 6100089700, "probabilidad_deslizamiento": 0.8717, "nivel_riesgo": "Alto", "timestamp": "2026-05-20T04:05:55.914632+00:00"}, {"hybas_id": 6100089630, "probabilidad_deslizamiento": 0.0221, "nivel_riesgo": "Bajo", "timestamp": "2026-05-20T04:05:55.914632+00:00"}, {"hybas_id": 6100089710, "probabilidad_deslizamiento": 0.8606, "nivel_riesgo": "Alto", "timestamp": "2026-05-20T04:05:55.914632+00:00"}, {"hybas_id": 6100087150, "probabilidad_deslizamiento": 0.0204, "nivel_riesgo": "Bajo", "timestamp": "2026-05-20T04:05:55.914632+00:00"}, {"hybas_id": 6100087100, "probabilidad_deslizamiento": 0.02, "nivel_riesgo": "Bajo", "timestamp": "2026-05-20T04:05:55.914632+00:00"}, {"hybas_id": 6100990020, "probabilidad_deslizamiento": 0.0219, "nivel_riesgo": "Bajo", "timestamp": "2026-05-20T04:05:55.914632+00:00"}, {"hybas_id": 6100989890, "probabilidad_deslizamiento": 0.592, "nivel_riesgo": "Medio", "timestamp": "2026-05-20T04:05:55.914632+00:00"}, {"hybas_id": 6100086420, "probabilidad_deslizamiento": 0.8737, "nivel_riesgo": "Alto", "timestamp": "2026-05-20T04:05:55.914632+00:00"}, {"hybas_id": 6100086270, "probabilidad_deslizamiento": 0.6594, "nivel_riesgo": "Alto", "timestamp": "2026-05-20T04:05:55.914632+00:00"}, {"hybas_id": 6100088570, "probabilidad_deslizamiento": 0.0904, "nivel_riesgo": "Bajo", "timestamp": "2026-05-20T04:05:55.914632+00:00"}, {"hybas_id": 6100991260, "probabilidad_deslizamiento": 0.8565, "nivel_riesgo": "Alto", "timestamp": "2026-05-20T04:05:55.914632+00:00"}, {"hybas_id": 6100991100, "probabilidad_deslizamiento": 0.7237, "nivel_riesgo": "Alto", "timestamp": "2026-05-20T04:05:55.914632+00:00"}, {"hybas_id": 6100990720, "probabilidad_deslizamiento": 0.6566, "nivel_riesgo": "Alto", "timestamp": "2026-05-20T04:05:55.914632+00:00"}, {"hybas_id": 6100990330, "probabilidad_deslizamiento": 0.8696, "nivel_riesgo": "Alto", "timestamp": "2026-05-20T04:05:55.914632+00:00"}, {"hybas_id": 6100990390, "probabilidad_deslizamiento": 0.6566, "nivel_riesgo": "Alto", "timestamp": "2026-05-20T04:05:55.914632+00:00"}, {"hybas_id": 6100990400, "probabilidad_deslizamiento": 0.6715, "nivel_riesgo": "Alto", "timestamp": "2026-05-20T04:05:55.914632+00:00"}, {"hybas_id": 6100080810, "probabilidad_deslizamiento": 0.8725, "nivel_riesgo": "Alto", "timestamp": "2026-05-20T04:05:55.914632+00:00"}, {"hybas_id": 6100986590, "probabilidad_deslizamiento": 0.7569, "nivel_riesgo": "Alto", "timestamp": "2026-05-20T04:05:55.914632+00:00"}, {"hybas_id": 6100078730, "probabilidad_deslizamiento": 0.0209, "nivel_riesgo": "Bajo", "timestamp": "2026-05-20T04:05:55.914632+00:00"}, {"hybas_id": 6100077630, "probabilidad_deslizamiento": 0.8691, "nivel_riesgo": "Alto", "timestamp": "2026-05-20T04:05:55.914632+00:00"}, {"hybas_id": 6100076110, "probabilidad_deslizamiento": 0.6668, "nivel_riesgo": "Alto", "timestamp": "2026-05-20T04:05:55.914632+00:00"}, {"hybas_id": 6100076120, "probabilidad_deslizamiento": 0.0192, "nivel_riesgo": "Bajo", "timestamp": "2026-05-20T04:05:55.914632+00:00"}, {"hybas_id": 6100985410, "probabilidad_deslizamiento": 0.7471, "nivel_riesgo": "Alto", "timestamp": "2026-05-20T04:05:55.914632+00:00"}, {"hybas_id": 6100075620, "probabilidad_deslizamiento": 0.8691, "nivel_riesgo": "Alto", "timestamp": "2026-05-20T04:05:55.914632+00:00"}, {"hybas_id": 6100985390, "probabilidad_deslizamiento": 0.672, "nivel_riesgo": "Alto", "timestamp": "2026-05-20T04:05:55.914632+00:00"}, {"hybas_id": 6100073970, "probabilidad_deslizamiento": 0.6668, "nivel_riesgo": "Alto", "timestamp": "2026-05-20T04:05:55.914632+00:00"}, {"hybas_id": 6100987200, "probabilidad_deslizamiento": 0.6824, "nivel_riesgo": "Alto", "timestamp": "2026-05-20T04:05:55.914632+00:00"}, {"hybas_id": 6100990120, "probabilidad_deslizamiento": 0.0203, "nivel_riesgo": "Bajo", "timestamp": "2026-05-20T04:05:55.914632+00:00"}, {"hybas_id": 6100989980, "probabilidad_deslizamiento": 0.6566, "nivel_riesgo": "Alto", "timestamp": "2026-05-20T04:05:55.914632+00:00"}, {"hybas_id": 6100085550, "probabilidad_deslizamiento": 0.6732, "nivel_riesgo": "Alto", "timestamp": "2026-05-20T04:05:55.914632+00:00"}, {"hybas_id": 6100086470, "probabilidad_deslizamiento": 0.0206, "nivel_riesgo": "Bajo", "timestamp": "2026-05-20T04:05:55.914632+00:00"}, {"hybas_id": 6100085500, "probabilidad_deslizamiento": 0.0192, "nivel_riesgo": "Bajo", "timestamp": "2026-05-20T04:05:55.914632+00:00"}, {"hybas_id": 6100082590, "probabilidad_deslizamiento": 0.8743, "nivel_riesgo": "Alto", "timestamp": "2026-05-20T04:05:55.914632+00:00"}, {"hybas_id": 6100083190, "probabilidad_deslizamiento": 0.8701, "nivel_riesgo": "Alto", "timestamp": "2026-05-20T04:05:55.914632+00:00"}, {"hybas_id": 6100082500, "probabilidad_deslizamiento": 0.6737, "nivel_riesgo": "Alto", "timestamp": "2026-05-20T04:05:55.914632+00:00"}, {"hybas_id": 6100083030, "probabilidad_deslizamiento": 0.0214, "nivel_riesgo": "Bajo", "timestamp": "2026-05-20T04:05:55.914632+00:00"}, {"hybas_id": 6100081230, "probabilidad_deslizamiento": 0.6566, "nivel_riesgo": "Alto", "timestamp": "2026-05-20T04:05:55.914632+00:00"}, {"hybas_id": 6100083820, "probabilidad_deslizamiento": 0.6739, "nivel_riesgo": "Alto", "timestamp": "2026-05-20T04:05:55.914632+00:00"}, {"hybas_id": 6100988420, "probabilidad_deslizamiento": 0.8394, "nivel_riesgo": "Alto", "timestamp": "2026-05-20T04:05:55.914632+00:00"}, {"hybas_id": 6100080880, "probabilidad_deslizamiento": 0.0207, "nivel_riesgo": "Bajo", "timestamp": "2026-05-20T04:05:55.914632+00:00"}, {"hybas_id": 6100078720, "probabilidad_deslizamiento": 0.0192, "nivel_riesgo": "Bajo", "timestamp": "2026-05-20T04:05:55.914632+00:00"}, {"hybas_id": 6100081290, "probabilidad_deslizamiento": 0.6731, "nivel_riesgo": "Alto", "timestamp": "2026-05-20T04:05:55.914632+00:00"}, {"hybas_id": 6100000220, "probabilidad_deslizamiento": 0.7284, "nivel_riesgo": "Alto", "timestamp": "2026-05-20T04:05:55.914632+00:00"}, {"hybas_id": 6100081280, "probabilidad_deslizamiento": 0.8748, "nivel_riesgo": "Alto", "timestamp": "2026-05-20T04:05:55.914632+00:00"}, {"hybas_id": 6100987560, "probabilidad_deslizamiento": 0.8454, "nivel_riesgo": "Alto", "timestamp": "2026-05-20T04:05:55.914632+00:00"}, {"hybas_id": 6100078040, "probabilidad_deslizamiento": 0.6815, "nivel_riesgo": "Alto", "timestamp": "2026-05-20T04:05:55.914632+00:00"}, {"hybas_id": 6100000210, "probabilidad_deslizamiento": 0.0206, "nivel_riesgo": "Bajo", "timestamp": "2026-05-20T04:05:55.914632+00:00"}, {"hybas_id": 6100000200, "probabilidad_deslizamiento": 0.6823, "nivel_riesgo": "Alto", "timestamp": "2026-05-20T04:05:55.914632+00:00"}, {"hybas_id": 6100988120, "probabilidad_deslizamiento": 0.6319, "nivel_riesgo": "Alto", "timestamp": "2026-05-20T04:05:55.914632+00:00"}, {"hybas_id": 6100081180, "probabilidad_deslizamiento": 0.681, "nivel_riesgo": "Alto", "timestamp": "2026-05-20T04:05:55.914632+00:00"}, {"hybas_id": 6100000230, "probabilidad_deslizamiento": 0.0192, "nivel_riesgo": "Bajo", "timestamp": "2026-05-20T04:05:55.914632+00:00"}, {"hybas_id": 6100080650, "probabilidad_deslizamiento": 0.8691, "nivel_riesgo": "Alto", "timestamp": "2026-05-20T04:05:55.914632+00:00"}, {"hybas_id": 6100080740, "probabilidad_deslizamiento": 0.6818, "nivel_riesgo": "Alto", "timestamp": "2026-05-20T04:05:55.914632+00:00"}, {"hybas_id": 6100000240, "probabilidad_deslizamiento": 0.6818, "nivel_riesgo": "Alto", "timestamp": "2026-05-20T04:05:55.914632+00:00"}, {"hybas_id": 6100000250, "probabilidad_deslizamiento": 0.0191, "nivel_riesgo": "Bajo", "timestamp": "2026-05-20T04:05:55.914632+00:00"}, {"hybas_id": 6100079080, "probabilidad_deslizamiento": 0.8691, "nivel_riesgo": "Alto", "timestamp": "2026-05-20T04:05:55.914632+00:00"}, {"hybas_id": 6100000260, "probabilidad_deslizamiento": 0.6692, "nivel_riesgo": "Alto", "timestamp": "2026-05-20T04:05:55.914632+00:00"}, {"hybas_id": 6100078990, "probabilidad_deslizamiento": 0.0192, "nivel_riesgo": "Bajo", "timestamp": "2026-05-20T04:05:55.914632+00:00"}, {"hybas_id": 6100000180, "probabilidad_deslizamiento": 0.0194, "nivel_riesgo": "Bajo", "timestamp": "2026-05-20T04:05:55.914632+00:00"}, {"hybas_id": 6100000170, "probabilidad_deslizamiento": 0.6737, "nivel_riesgo": "Alto", "timestamp": "2026-05-20T04:05:55.914632+00:00"}, {"hybas_id": 6100000270, "probabilidad_deslizamiento": 0.0191, "nivel_riesgo": "Bajo", "timestamp": "2026-05-20T04:05:55.914632+00:00"}, {"hybas_id": 6100000280, "probabilidad_deslizamiento": 0.0227, "nivel_riesgo": "Bajo", "timestamp": "2026-05-20T04:05:55.914632+00:00"}, {"hybas_id": 6100000290, "probabilidad_deslizamiento": 0.0191, "nivel_riesgo": "Bajo", "timestamp": "2026-05-20T04:05:55.914632+00:00"}, {"hybas_id": 6100000300, "probabilidad_deslizamiento": 0.0192, "nivel_riesgo": "Bajo", "timestamp": "2026-05-20T04:05:55.914632+00:00"}, {"hybas_id": 6100075240, "probabilidad_deslizamiento": 0.0202, "nivel_riesgo": "Bajo", "timestamp": "2026-05-20T04:05:55.914632+00:00"}, {"hybas_id": 6100075200, "probabilidad_deslizamiento": 0.6726, "nivel_riesgo": "Alto", "timestamp": "2026-05-20T04:05:55.914632+00:00"}, {"hybas_id": 6100074340, "probabilidad_deslizamiento": 0.6763, "nivel_riesgo": "Alto", "timestamp": "2026-05-20T04:05:55.914632+00:00"}, {"hybas_id": 6100074280, "probabilidad_deslizamiento": 0.0192, "nivel_riesgo": "Bajo", "timestamp": "2026-05-20T04:05:55.914632+00:00"}, {"hybas_id": 6100000310, "probabilidad_deslizamiento": 0.8717, "nivel_riesgo": "Alto", "timestamp": "2026-05-20T04:05:55.914632+00:00"}, {"hybas_id": 6100073780, "probabilidad_deslizamiento": 0.6818, "nivel_riesgo": "Alto", "timestamp": "2026-05-20T04:05:55.914632+00:00"}, {"hybas_id": 6100073920, "probabilidad_deslizamiento": 0.0191, "nivel_riesgo": "Bajo", "timestamp": "2026-05-20T04:05:55.914632+00:00"}, {"hybas_id": 6100984480, "probabilidad_deslizamiento": 0.672, "nivel_riesgo": "Alto", "timestamp": "2026-05-20T04:05:55.914632+00:00"}, {"hybas_id": 6100072310, "probabilidad_deslizamiento": 0.0193, "nivel_riesgo": "Bajo", "timestamp": "2026-05-20T04:05:55.914632+00:00"}, {"hybas_id": 6100072300, "probabilidad_deslizamiento": 0.6762, "nivel_riesgo": "Alto", "timestamp": "2026-05-20T04:05:55.914632+00:00"}, {"hybas_id": 6100984100, "probabilidad_deslizamiento": 0.6739, "nivel_riesgo": "Alto", "timestamp": "2026-05-20T04:05:55.914632+00:00"}, {"hybas_id": 6100071870, "probabilidad_deslizamiento": 0.0209, "nivel_riesgo": "Bajo", "timestamp": "2026-05-20T04:05:55.914632+00:00"}, {"hybas_id": 6100983710, "probabilidad_deslizamiento": 0.0202, "nivel_riesgo": "Bajo", "timestamp": "2026-05-20T04:05:55.914632+00:00"}, {"hybas_id": 6100071840, "probabilidad_deslizamiento": 0.681, "nivel_riesgo": "Alto", "timestamp": "2026-05-20T04:05:55.914632+00:00"}, {"hybas_id": 6100000360, "probabilidad_deslizamiento": 0.6814, "nivel_riesgo": "Alto", "timestamp": "2026-05-20T04:05:55.914632+00:00"}, {"hybas_id": 6100073730, "probabilidad_deslizamiento": 0.0203, "nivel_riesgo": "Bajo", "timestamp": "2026-05-20T04:05:55.914632+00:00"}, {"hybas_id": 6100000340, "probabilidad_deslizamiento": 0.6815, "nivel_riesgo": "Alto", "timestamp": "2026-05-20T04:05:55.914632+00:00"}, {"hybas_id": 6100000320, "probabilidad_deslizamiento": 0.0191, "nivel_riesgo": "Bajo", "timestamp": "2026-05-20T04:05:55.914632+00:00"}, {"hybas_id": 6100000330, "probabilidad_deslizamiento": 0.0199, "nivel_riesgo": "Bajo", "timestamp": "2026-05-20T04:05:55.914632+00:00"}, {"hybas_id": 6100000350, "probabilidad_deslizamiento": 0.8576, "nivel_riesgo": "Alto", "timestamp": "2026-05-20T04:05:55.914632+00:00"}, {"hybas_id": 6100985430, "probabilidad_deslizamiento": 0.681, "nivel_riesgo": "Alto", "timestamp": "2026-05-20T04:05:55.914632+00:00"}, {"hybas_id": 6100072660, "probabilidad_deslizamiento": 0.8691, "nivel_riesgo": "Alto", "timestamp": "2026-05-20T04:05:55.914632+00:00"}, {"hybas_id": 6100000380, "probabilidad_deslizamiento": 0.7227, "nivel_riesgo": "Alto", "timestamp": "2026-05-20T04:05:55.914632+00:00"}, {"hybas_id": 6100000370, "probabilidad_deslizamiento": 0.0192, "nivel_riesgo": "Bajo", "timestamp": "2026-05-20T04:05:55.914632+00:00"}, {"hybas_id": 6100107350, "probabilidad_deslizamiento": 0.7007, "nivel_riesgo": "Alto", "timestamp": "2026-05-20T04:05:55.914632+00:00"}, {"hybas_id": 6100106480, "probabilidad_deslizamiento": 0.7007, "nivel_riesgo": "Alto", "timestamp": "2026-05-20T04:05:55.914632+00:00"}, {"hybas_id": 6100105730, "probabilidad_deslizamiento": 0.8806, "nivel_riesgo": "Alto", "timestamp": "2026-05-20T04:05:55.914632+00:00"}, {"hybas_id": 6100105250, "probabilidad_deslizamiento": 0.7017, "nivel_riesgo": "Alto", "timestamp": "2026-05-20T04:05:55.914632+00:00"}, {"hybas_id": 6100104150, "probabilidad_deslizamiento": 0.6994, "nivel_riesgo": "Alto", "timestamp": "2026-05-20T04:05:55.914632+00:00"}, {"hybas_id": 6100103650, "probabilidad_deslizamiento": 0.0402, "nivel_riesgo": "Bajo", "timestamp": "2026-05-20T04:05:55.914632+00:00"}, {"hybas_id": 6100103680, "probabilidad_deslizamiento": 0.7017, "nivel_riesgo": "Alto", "timestamp": "2026-05-20T04:05:55.914632+00:00"}, {"hybas_id": 6100102980, "probabilidad_deslizamiento": 0.7001, "nivel_riesgo": "Alto", "timestamp": "2026-05-20T04:05:55.914632+00:00"}, {"hybas_id": 6100102530, "probabilidad_deslizamiento": 0.7008, "nivel_riesgo": "Alto", "timestamp": "2026-05-20T04:05:55.914632+00:00"}, {"hybas_id": 6100102120, "probabilidad_deslizamiento": 0.7018, "nivel_riesgo": "Alto", "timestamp": "2026-05-20T04:05:55.914632+00:00"}, {"hybas_id": 6100102080, "probabilidad_deslizamiento": 0.7003, "nivel_riesgo": "Alto", "timestamp": "2026-05-20T04:05:55.914632+00:00"}, {"hybas_id": 6100101420, "probabilidad_deslizamiento": 0.7008, "nivel_riesgo": "Alto", "timestamp": "2026-05-20T04:05:55.914632+00:00"}, {"hybas_id": 6100100810, "probabilidad_deslizamiento": 0.7012, "nivel_riesgo": "Alto", "timestamp": "2026-05-20T04:05:55.914632+00:00"}, {"hybas_id": 6100098640, "probabilidad_deslizamiento": 0.7012, "nivel_riesgo": "Alto", "timestamp": "2026-05-20T04:05:55.914632+00:00"}, {"hybas_id": 6100101560, "probabilidad_deslizamiento": 0.7002, "nivel_riesgo": "Alto", "timestamp": "2026-05-20T04:05:55.914632+00:00"}, {"hybas_id": 6100100530, "probabilidad_deslizamiento": 0.7023, "nivel_riesgo": "Alto", "timestamp": "2026-05-20T04:05:55.914632+00:00"}, {"hybas_id": 6100099660, "probabilidad_deslizamiento": 0.8687, "nivel_riesgo": "Alto", "timestamp": "2026-05-20T04:05:55.914632+00:00"}, {"hybas_id": 6100100740, "probabilidad_deslizamiento": 0.8632, "nivel_riesgo": "Alto", "timestamp": "2026-05-20T04:05:55.914632+00:00"}, {"hybas_id": 6100098590, "probabilidad_deslizamiento": 0.8652, "nivel_riesgo": "Alto", "timestamp": "2026-05-20T04:05:55.914632+00:00"}, {"hybas_id": 6100097870, "probabilidad_deslizamiento": 0.7016, "nivel_riesgo": "Alto", "timestamp": "2026-05-20T04:05:55.914632+00:00"}, {"hybas_id": 6100097760, "probabilidad_deslizamiento": 0.0417, "nivel_riesgo": "Bajo", "timestamp": "2026-05-20T04:05:55.914632+00:00"}, {"hybas_id": 6100097060, "probabilidad_deslizamiento": 0.0373, "nivel_riesgo": "Bajo", "timestamp": "2026-05-20T04:05:55.914632+00:00"}, {"hybas_id": 6100096860, "probabilidad_deslizamiento": 0.0389, "nivel_riesgo": "Bajo", "timestamp": "2026-05-20T04:05:55.914632+00:00"}, {"hybas_id": 6100096110, "probabilidad_deslizamiento": 0.7013, "nivel_riesgo": "Alto", "timestamp": "2026-05-20T04:05:55.914632+00:00"}, {"hybas_id": 6100097100, "probabilidad_deslizamiento": 0.7016, "nivel_riesgo": "Alto", "timestamp": "2026-05-20T04:05:55.914632+00:00"}, {"hybas_id": 6100097070, "probabilidad_deslizamiento": 0.7021, "nivel_riesgo": "Alto", "timestamp": "2026-05-20T04:05:55.914632+00:00"}, {"hybas_id": 6100096480, "probabilidad_deslizamiento": 0.7101, "nivel_riesgo": "Alto", "timestamp": "2026-05-20T04:05:55.914632+00:00"}, {"hybas_id": 6100095830, "probabilidad_deslizamiento": 0.6975, "nivel_riesgo": "Alto", "timestamp": "2026-05-20T04:05:55.914632+00:00"}, {"hybas_id": 6100095550, "probabilidad_deslizamiento": 0.6828, "nivel_riesgo": "Alto", "timestamp": "2026-05-20T04:05:55.914632+00:00"}, {"hybas_id": 6100095800, "probabilidad_deslizamiento": 0.6717, "nivel_riesgo": "Alto", "timestamp": "2026-05-20T04:05:55.914632+00:00"}, {"hybas_id": 6100111070, "probabilidad_deslizamiento": 0.8065, "nivel_riesgo": "Alto", "timestamp": "2026-05-20T04:05:55.914632+00:00"}, {"hybas_id": 6100110470, "probabilidad_deslizamiento": 0.7026, "nivel_riesgo": "Alto", "timestamp": "2026-05-20T04:05:55.914632+00:00"}, {"hybas_id": 6100108950, "probabilidad_deslizamiento": 0.0453, "nivel_riesgo": "Bajo", "timestamp": "2026-05-20T04:05:55.914632+00:00"}, {"hybas_id": 6100109040, "probabilidad_deslizamiento": 0.6979, "nivel_riesgo": "Alto", "timestamp": "2026-05-20T04:05:55.914632+00:00"}, {"hybas_id": 6100110300, "probabilidad_deslizamiento": 0.1058, "nivel_riesgo": "Bajo", "timestamp": "2026-05-20T04:05:55.914632+00:00"}, {"hybas_id": 6100108550, "probabilidad_deslizamiento": 0.7027, "nivel_riesgo": "Alto", "timestamp": "2026-05-20T04:05:55.914632+00:00"}, {"hybas_id": 6100108450, "probabilidad_deslizamiento": 0.8824, "nivel_riesgo": "Alto", "timestamp": "2026-05-20T04:05:55.914632+00:00"}, {"hybas_id": 6100109050, "probabilidad_deslizamiento": 0.6971, "nivel_riesgo": "Alto", "timestamp": "2026-05-20T04:05:55.914632+00:00"}, {"hybas_id": 6100108860, "probabilidad_deslizamiento": 0.8751, "nivel_riesgo": "Alto", "timestamp": "2026-05-20T04:05:55.914632+00:00"}, {"hybas_id": 6100106020, "probabilidad_deslizamiento": 0.0372, "nivel_riesgo": "Bajo", "timestamp": "2026-05-20T04:05:55.914632+00:00"}, {"hybas_id": 6100106010, "probabilidad_deslizamiento": 0.8804, "nivel_riesgo": "Alto", "timestamp": "2026-05-20T04:05:55.914632+00:00"}, {"hybas_id": 6100105770, "probabilidad_deslizamiento": 0.6841, "nivel_riesgo": "Alto", "timestamp": "2026-05-20T04:05:55.914632+00:00"}, {"hybas_id": 6100105540, "probabilidad_deslizamiento": 0.7006, "nivel_riesgo": "Alto", "timestamp": "2026-05-20T04:05:55.914632+00:00"}, {"hybas_id": 6100998500, "probabilidad_deslizamiento": 0.0693, "nivel_riesgo": "Bajo", "timestamp": "2026-05-20T04:05:55.914632+00:00"}, {"hybas_id": 6100105720, "probabilidad_deslizamiento": 0.6787, "nivel_riesgo": "Alto", "timestamp": "2026-05-20T04:05:55.914632+00:00"}, {"hybas_id": 6100998540, "probabilidad_deslizamiento": 0.8713, "nivel_riesgo": "Alto", "timestamp": "2026-05-20T04:05:55.914632+00:00"}, {"hybas_id": 6100105450, "probabilidad_deslizamiento": 0.6987, "nivel_riesgo": "Alto", "timestamp": "2026-05-20T04:05:55.914632+00:00"}, {"hybas_id": 6100107280, "probabilidad_deslizamiento": 0.6997, "nivel_riesgo": "Alto", "timestamp": "2026-05-20T04:05:55.914632+00:00"}, {"hybas_id": 6100106280, "probabilidad_deslizamiento": 0.7548, "nivel_riesgo": "Alto", "timestamp": "2026-05-20T04:05:55.914632+00:00"}, {"hybas_id": 6100104840, "probabilidad_deslizamiento": 0.8775, "nivel_riesgo": "Alto", "timestamp": "2026-05-20T04:05:55.914632+00:00"}, {"hybas_id": 6100104860, "probabilidad_deslizamiento": 0.0395, "nivel_riesgo": "Bajo", "timestamp": "2026-05-20T04:05:55.914632+00:00"}, {"hybas_id": 6100105240, "probabilidad_deslizamiento": 0.0382, "nivel_riesgo": "Bajo", "timestamp": "2026-05-20T04:05:55.914632+00:00"}, {"hybas_id": 6100104850, "probabilidad_deslizamiento": 0.6979, "nivel_riesgo": "Alto", "timestamp": "2026-05-20T04:05:55.914632+00:00"}, {"hybas_id": 6100104710, "probabilidad_deslizamiento": 0.7898, "nivel_riesgo": "Alto", "timestamp": "2026-05-20T04:05:55.914632+00:00"}, {"hybas_id": 6100104080, "probabilidad_deslizamiento": 0.6952, "nivel_riesgo": "Alto", "timestamp": "2026-05-20T04:05:55.914632+00:00"}, {"hybas_id": 6100102390, "probabilidad_deslizamiento": 0.8843, "nivel_riesgo": "Alto", "timestamp": "2026-05-20T04:05:55.914632+00:00"}, {"hybas_id": 6100102890, "probabilidad_deslizamiento": 0.0375, "nivel_riesgo": "Bajo", "timestamp": "2026-05-20T04:05:55.914632+00:00"}, {"hybas_id": 6100104210, "probabilidad_deslizamiento": 0.869, "nivel_riesgo": "Alto", "timestamp": "2026-05-20T04:05:55.914632+00:00"}, {"hybas_id": 6100104400, "probabilidad_deslizamiento": 0.6936, "nivel_riesgo": "Alto", "timestamp": "2026-05-20T04:05:55.914632+00:00"}, {"hybas_id": 6100104140, "probabilidad_deslizamiento": 0.7013, "nivel_riesgo": "Alto", "timestamp": "2026-05-20T04:05:55.914632+00:00"}, {"hybas_id": 6100104070, "probabilidad_deslizamiento": 0.0378, "nivel_riesgo": "Bajo", "timestamp": "2026-05-20T04:05:55.914632+00:00"}, {"hybas_id": 6100104130, "probabilidad_deslizamiento": 0.0424, "nivel_riesgo": "Bajo", "timestamp": "2026-05-20T04:05:55.914632+00:00"}, {"hybas_id": 6100104340, "probabilidad_deslizamiento": 0.0417, "nivel_riesgo": "Bajo", "timestamp": "2026-05-20T04:05:55.914632+00:00"}, {"hybas_id": 6100101520, "probabilidad_deslizamiento": 0.8705, "nivel_riesgo": "Alto", "timestamp": "2026-05-20T04:05:55.914632+00:00"}, {"hybas_id": 6100101130, "probabilidad_deslizamiento": 0.6996, "nivel_riesgo": "Alto", "timestamp": "2026-05-20T04:05:55.914632+00:00"}, {"hybas_id": 6100996840, "probabilidad_deslizamiento": 0.8677, "nivel_riesgo": "Alto", "timestamp": "2026-05-20T04:05:55.914632+00:00"}, {"hybas_id": 6100101410, "probabilidad_deslizamiento": 0.7003, "nivel_riesgo": "Alto", "timestamp": "2026-05-20T04:05:55.914632+00:00"}, {"hybas_id": 6100101550, "probabilidad_deslizamiento": 0.7001, "nivel_riesgo": "Alto", "timestamp": "2026-05-20T04:05:55.914632+00:00"}, {"hybas_id": 6100102230, "probabilidad_deslizamiento": 0.7006, "nivel_riesgo": "Alto", "timestamp": "2026-05-20T04:05:55.914632+00:00"}, {"hybas_id": 6100101620, "probabilidad_deslizamiento": 0.7001, "nivel_riesgo": "Alto", "timestamp": "2026-05-20T04:05:55.914632+00:00"}, {"hybas_id": 6100101530, "probabilidad_deslizamiento": 0.7002, "nivel_riesgo": "Alto", "timestamp": "2026-05-20T04:05:55.914632+00:00"}, {"hybas_id": 6100996730, "probabilidad_deslizamiento": 0.8224, "nivel_riesgo": "Alto", "timestamp": "2026-05-20T04:05:55.914632+00:00"}, {"hybas_id": 6100099650, "probabilidad_deslizamiento": 0.0425, "nivel_riesgo": "Bajo", "timestamp": "2026-05-20T04:05:55.914632+00:00"}, {"hybas_id": 6100996560, "probabilidad_deslizamiento": 0.8687, "nivel_riesgo": "Alto", "timestamp": "2026-05-20T04:05:55.914632+00:00"}, {"hybas_id": 6100099570, "probabilidad_deslizamiento": 0.7001, "nivel_riesgo": "Alto", "timestamp": "2026-05-20T04:05:55.914632+00:00"}, {"hybas_id": 6100096990, "probabilidad_deslizamiento": 0.8813, "nivel_riesgo": "Alto", "timestamp": "2026-05-20T04:05:55.914632+00:00"}, {"hybas_id": 6100096740, "probabilidad_deslizamiento": 0.0382, "nivel_riesgo": "Bajo", "timestamp": "2026-05-20T04:05:55.914632+00:00"}, {"hybas_id": 6100997020, "probabilidad_deslizamiento": 0.7, "nivel_riesgo": "Alto", "timestamp": "2026-05-20T04:05:55.914632+00:00"}, {"hybas_id": 6100102440, "probabilidad_deslizamiento": 0.0479, "nivel_riesgo": "Bajo", "timestamp": "2026-05-20T04:05:55.914632+00:00"}, {"hybas_id": 6100101020, "probabilidad_deslizamiento": 0.0432, "nivel_riesgo": "Bajo", "timestamp": "2026-05-20T04:05:55.914632+00:00"}, {"hybas_id": 6100996360, "probabilidad_deslizamiento": 0.6959, "nivel_riesgo": "Alto", "timestamp": "2026-05-20T04:05:55.914632+00:00"}, {"hybas_id": 6100099140, "probabilidad_deslizamiento": 0.0241, "nivel_riesgo": "Bajo", "timestamp": "2026-05-20T04:05:55.914632+00:00"}, {"hybas_id": 6100099190, "probabilidad_deslizamiento": 0.6801, "nivel_riesgo": "Alto", "timestamp": "2026-05-20T04:05:55.914632+00:00"}, {"hybas_id": 6100098170, "probabilidad_deslizamiento": 0.6901, "nivel_riesgo": "Alto", "timestamp": "2026-05-20T04:05:55.914632+00:00"}, {"hybas_id": 6100097500, "probabilidad_deslizamiento": 0.8744, "nivel_riesgo": "Alto", "timestamp": "2026-05-20T04:05:55.914632+00:00"}, {"hybas_id": 6100995470, "probabilidad_deslizamiento": 0.6836, "nivel_riesgo": "Alto", "timestamp": "2026-05-20T04:05:55.914632+00:00"}, {"hybas_id": 6100097460, "probabilidad_deslizamiento": 0.6832, "nivel_riesgo": "Alto", "timestamp": "2026-05-20T04:05:55.914632+00:00"}, {"hybas_id": 6100996430, "probabilidad_deslizamiento": 0.3244, "nivel_riesgo": "Medio", "timestamp": "2026-05-20T04:05:55.914632+00:00"}, {"hybas_id": 6100996300, "probabilidad_deslizamiento": 0.6976, "nivel_riesgo": "Alto", "timestamp": "2026-05-20T04:05:55.914632+00:00"}, {"hybas_id": 6100996230, "probabilidad_deslizamiento": 0.6794, "nivel_riesgo": "Alto", "timestamp": "2026-05-20T04:05:55.914632+00:00"}, {"hybas_id": 6100996250, "probabilidad_deslizamiento": 0.6987, "nivel_riesgo": "Alto", "timestamp": "2026-05-20T04:05:55.914632+00:00"}, {"hybas_id": 6100995660, "probabilidad_deslizamiento": 0.6807, "nivel_riesgo": "Alto", "timestamp": "2026-05-20T04:05:55.914632+00:00"}, {"hybas_id": 6100995490, "probabilidad_deslizamiento": 0.0414, "nivel_riesgo": "Bajo", "timestamp": "2026-05-20T04:05:55.914632+00:00"}, {"hybas_id": 6100995020, "probabilidad_deslizamiento": 0.6826, "nivel_riesgo": "Alto", "timestamp": "2026-05-20T04:05:55.914632+00:00"}, {"hybas_id": 6100994540, "probabilidad_deslizamiento": 0.848, "nivel_riesgo": "Alto", "timestamp": "2026-05-20T04:05:55.914632+00:00"}, {"hybas_id": 6100994210, "probabilidad_deslizamiento": 0.6834, "nivel_riesgo": "Alto", "timestamp": "2026-05-20T04:05:55.914632+00:00"}, {"hybas_id": 6100094210, "probabilidad_deslizamiento": 0.6757, "nivel_riesgo": "Alto", "timestamp": "2026-05-20T04:05:55.914632+00:00"}, {"hybas_id": 6100096180, "probabilidad_deslizamiento": 0.6978, "nivel_riesgo": "Alto", "timestamp": "2026-05-20T04:05:55.914632+00:00"}, {"hybas_id": 6100096640, "probabilidad_deslizamiento": 0.8771, "nivel_riesgo": "Alto", "timestamp": "2026-05-20T04:05:55.914632+00:00"}, {"hybas_id": 6100096100, "probabilidad_deslizamiento": 0.0412, "nivel_riesgo": "Bajo", "timestamp": "2026-05-20T04:05:55.914632+00:00"}, {"hybas_id": 6100095280, "probabilidad_deslizamiento": 0.041, "nivel_riesgo": "Bajo", "timestamp": "2026-05-20T04:05:55.914632+00:00"}, {"hybas_id": 6100095020, "probabilidad_deslizamiento": 0.6991, "nivel_riesgo": "Alto", "timestamp": "2026-05-20T04:05:55.914632+00:00"}, {"hybas_id": 6100095170, "probabilidad_deslizamiento": 0.0377, "nivel_riesgo": "Bajo", "timestamp": "2026-05-20T04:05:55.914632+00:00"}, {"hybas_id": 6100094940, "probabilidad_deslizamiento": 0.8839, "nivel_riesgo": "Alto", "timestamp": "2026-05-20T04:05:55.914632+00:00"}, {"hybas_id": 6100092280, "probabilidad_deslizamiento": 0.022, "nivel_riesgo": "Bajo", "timestamp": "2026-05-20T04:05:55.914632+00:00"}, {"hybas_id": 6100092320, "probabilidad_deslizamiento": 0.0207, "nivel_riesgo": "Bajo", "timestamp": "2026-05-20T04:05:55.914632+00:00"}, {"hybas_id": 6100993180, "probabilidad_deslizamiento": 0.0418, "nivel_riesgo": "Bajo", "timestamp": "2026-05-20T04:05:55.914632+00:00"}, {"hybas_id": 6100094960, "probabilidad_deslizamiento": 0.8462, "nivel_riesgo": "Alto", "timestamp": "2026-05-20T04:05:55.914632+00:00"}, {"hybas_id": 6100094080, "probabilidad_deslizamiento": 0.6823, "nivel_riesgo": "Alto", "timestamp": "2026-05-20T04:05:55.914632+00:00"}, {"hybas_id": 6100093010, "probabilidad_deslizamiento": 0.6941, "nivel_riesgo": "Alto", "timestamp": "2026-05-20T04:05:55.914632+00:00"}, {"hybas_id": 6100092910, "probabilidad_deslizamiento": 0.6826, "nivel_riesgo": "Alto", "timestamp": "2026-05-20T04:05:55.914632+00:00"}, {"hybas_id": 6100094950, "probabilidad_deslizamiento": 0.6819, "nivel_riesgo": "Alto", "timestamp": "2026-05-20T04:05:55.914632+00:00"}, {"hybas_id": 6100994410, "probabilidad_deslizamiento": 0.8199, "nivel_riesgo": "Alto", "timestamp": "2026-05-20T04:05:55.914632+00:00"}, {"hybas_id": 6100094230, "probabilidad_deslizamiento": 0.6823, "nivel_riesgo": "Alto", "timestamp": "2026-05-20T04:05:55.914632+00:00"}, {"hybas_id": 6100094130, "probabilidad_deslizamiento": 0.0257, "nivel_riesgo": "Bajo", "timestamp": "2026-05-20T04:05:55.914632+00:00"}, {"hybas_id": 6100092190, "probabilidad_deslizamiento": 0.0255, "nivel_riesgo": "Bajo", "timestamp": "2026-05-20T04:05:55.914632+00:00"}, {"hybas_id": 6100092180, "probabilidad_deslizamiento": 0.6766, "nivel_riesgo": "Alto", "timestamp": "2026-05-20T04:05:55.914632+00:00"}, {"hybas_id": 6100993300, "probabilidad_deslizamiento": 0.6746, "nivel_riesgo": "Alto", "timestamp": "2026-05-20T04:05:55.914632+00:00"}, {"hybas_id": 6100090820, "probabilidad_deslizamiento": 0.739, "nivel_riesgo": "Alto", "timestamp": "2026-05-20T04:05:55.914632+00:00"}, {"hybas_id": 6100092090, "probabilidad_deslizamiento": 0.6801, "nivel_riesgo": "Alto", "timestamp": "2026-05-20T04:05:55.914632+00:00"}, {"hybas_id": 6100092100, "probabilidad_deslizamiento": 0.6812, "nivel_riesgo": "Alto", "timestamp": "2026-05-20T04:05:55.914632+00:00"}, {"hybas_id": 6100095870, "probabilidad_deslizamiento": 0.6986, "nivel_riesgo": "Alto", "timestamp": "2026-05-20T04:05:55.914632+00:00"}, {"hybas_id": 6100096940, "probabilidad_deslizamiento": 0.8812, "nivel_riesgo": "Alto", "timestamp": "2026-05-20T04:05:55.914632+00:00"}, {"hybas_id": 6100095790, "probabilidad_deslizamiento": 0.7029, "nivel_riesgo": "Alto", "timestamp": "2026-05-20T04:05:55.914632+00:00"}, {"hybas_id": 6100095880, "probabilidad_deslizamiento": 0.7012, "nivel_riesgo": "Alto", "timestamp": "2026-05-20T04:05:55.914632+00:00"}, {"hybas_id": 6100993810, "probabilidad_deslizamiento": 0.6917, "nivel_riesgo": "Alto", "timestamp": "2026-05-20T04:05:55.914632+00:00"}, {"hybas_id": 6100993510, "probabilidad_deslizamiento": 0.6772, "nivel_riesgo": "Alto", "timestamp": "2026-05-20T04:05:55.914632+00:00"}, {"hybas_id": 6100993400, "probabilidad_deslizamiento": 0.6995, "nivel_riesgo": "Alto", "timestamp": "2026-05-20T04:05:55.914632+00:00"}, {"hybas_id": 6100993190, "probabilidad_deslizamiento": 0.6805, "nivel_riesgo": "Alto", "timestamp": "2026-05-20T04:05:55.914632+00:00"}, {"hybas_id": 6100992220, "probabilidad_deslizamiento": 0.6579, "nivel_riesgo": "Alto", "timestamp": "2026-05-20T04:05:55.914632+00:00"}, {"hybas_id": 6100091680, "probabilidad_deslizamiento": 0.0269, "nivel_riesgo": "Bajo", "timestamp": "2026-05-20T04:05:55.914632+00:00"}, {"hybas_id": 6100092480, "probabilidad_deslizamiento": 0.6829, "nivel_riesgo": "Alto", "timestamp": "2026-05-20T04:05:55.914632+00:00"}, {"hybas_id": 6100091400, "probabilidad_deslizamiento": 0.8446, "nivel_riesgo": "Alto", "timestamp": "2026-05-20T04:05:55.914632+00:00"}, {"hybas_id": 6100091390, "probabilidad_deslizamiento": 0.0211, "nivel_riesgo": "Bajo", "timestamp": "2026-05-20T04:05:55.914632+00:00"}, {"hybas_id": 6100091040, "probabilidad_deslizamiento": 0.6824, "nivel_riesgo": "Alto", "timestamp": "2026-05-20T04:05:55.914632+00:00"}, {"hybas_id": 6100090980, "probabilidad_deslizamiento": 0.6743, "nivel_riesgo": "Alto", "timestamp": "2026-05-20T04:05:55.914632+00:00"}, {"hybas_id": 6100090640, "probabilidad_deslizamiento": 0.6823, "nivel_riesgo": "Alto", "timestamp": "2026-05-20T04:05:55.914632+00:00"}, {"hybas_id": 6100089740, "probabilidad_deslizamiento": 0.6808, "nivel_riesgo": "Alto", "timestamp": "2026-05-20T04:05:55.914632+00:00"}, {"hybas_id": 6100088820, "probabilidad_deslizamiento": 0.8717, "nivel_riesgo": "Alto", "timestamp": "2026-05-20T04:05:55.914632+00:00"}, {"hybas_id": 6100091230, "probabilidad_deslizamiento": 0.6807, "nivel_riesgo": "Alto", "timestamp": "2026-05-20T04:05:55.914632+00:00"}, {"hybas_id": 6100090900, "probabilidad_deslizamiento": 0.6808, "nivel_riesgo": "Alto", "timestamp": "2026-05-20T04:05:55.914632+00:00"}, {"hybas_id": 6100091690, "probabilidad_deslizamiento": 0.6799, "nivel_riesgo": "Alto", "timestamp": "2026-05-20T04:05:55.914632+00:00"}, {"hybas_id": 6100090750, "probabilidad_deslizamiento": 0.681, "nivel_riesgo": "Alto", "timestamp": "2026-05-20T04:05:55.914632+00:00"}, {"hybas_id": 6100091160, "probabilidad_deslizamiento": 0.7809, "nivel_riesgo": "Alto", "timestamp": "2026-05-20T04:05:55.914632+00:00"}, {"hybas_id": 6100090680, "probabilidad_deslizamiento": 0.6963, "nivel_riesgo": "Alto", "timestamp": "2026-05-20T04:05:55.914632+00:00"}, {"hybas_id": 6100090810, "probabilidad_deslizamiento": 0.8646, "nivel_riesgo": "Alto", "timestamp": "2026-05-20T04:05:55.914632+00:00"}, {"hybas_id": 6100090490, "probabilidad_deslizamiento": 0.0234, "nivel_riesgo": "Bajo", "timestamp": "2026-05-20T04:05:55.914632+00:00"}, {"hybas_id": 6100087980, "probabilidad_deslizamiento": 0.6822, "nivel_riesgo": "Alto", "timestamp": "2026-05-20T04:05:55.914632+00:00"}, {"hybas_id": 6100991080, "probabilidad_deslizamiento": 0.0454, "nivel_riesgo": "Bajo", "timestamp": "2026-05-20T04:05:55.914632+00:00"}, {"hybas_id": 6100087080, "probabilidad_deslizamiento": 0.6768, "nivel_riesgo": "Alto", "timestamp": "2026-05-20T04:05:55.914632+00:00"}, {"hybas_id": 6100990150, "probabilidad_deslizamiento": 0.6764, "nivel_riesgo": "Alto", "timestamp": "2026-05-20T04:05:55.914632+00:00"}, {"hybas_id": 6100989320, "probabilidad_deslizamiento": 0.6051, "nivel_riesgo": "Alto", "timestamp": "2026-05-20T04:05:55.914632+00:00"}, {"hybas_id": 6100083220, "probabilidad_deslizamiento": 0.6712, "nivel_riesgo": "Alto", "timestamp": "2026-05-20T04:05:55.914632+00:00"}, {"hybas_id": 6100989090, "probabilidad_deslizamiento": 0.021, "nivel_riesgo": "Bajo", "timestamp": "2026-05-20T04:05:55.914632+00:00"}, {"hybas_id": 6100988530, "probabilidad_deslizamiento": 0.0214, "nivel_riesgo": "Bajo", "timestamp": "2026-05-20T04:05:55.914632+00:00"}, {"hybas_id": 6100083050, "probabilidad_deslizamiento": 0.0195, "nivel_riesgo": "Bajo", "timestamp": "2026-05-20T04:05:55.914632+00:00"}, {"hybas_id": 6100988690, "probabilidad_deslizamiento": 0.6602, "nivel_riesgo": "Alto", "timestamp": "2026-05-20T04:05:55.914632+00:00"}, {"hybas_id": 6100094220, "probabilidad_deslizamiento": 0.6834, "nivel_riesgo": "Alto", "timestamp": "2026-05-20T04:05:55.914632+00:00"}, {"hybas_id": 6100092170, "probabilidad_deslizamiento": 0.0212, "nivel_riesgo": "Bajo", "timestamp": "2026-05-20T04:05:55.914632+00:00"}, {"hybas_id": 6100092310, "probabilidad_deslizamiento": 0.0211, "nivel_riesgo": "Bajo", "timestamp": "2026-05-20T04:05:55.914632+00:00"}, {"hybas_id": 6100092300, "probabilidad_deslizamiento": 0.8756, "nivel_riesgo": "Alto", "timestamp": "2026-05-20T04:05:55.914632+00:00"}, {"hybas_id": 6100091070, "probabilidad_deslizamiento": 0.6769, "nivel_riesgo": "Alto", "timestamp": "2026-05-20T04:05:55.914632+00:00"}, {"hybas_id": 6100992360, "probabilidad_deslizamiento": 0.685, "nivel_riesgo": "Alto", "timestamp": "2026-05-20T04:05:55.914632+00:00"}, {"hybas_id": 6100991350, "probabilidad_deslizamiento": 0.0207, "nivel_riesgo": "Bajo", "timestamp": "2026-05-20T04:05:55.914632+00:00"}, {"hybas_id": 6100089120, "probabilidad_deslizamiento": 0.8589, "nivel_riesgo": "Alto", "timestamp": "2026-05-20T04:05:55.914632+00:00"}, {"hybas_id": 6100088650, "probabilidad_deslizamiento": 0.6846, "nivel_riesgo": "Alto", "timestamp": "2026-05-20T04:05:55.914632+00:00"}, {"hybas_id": 6100087570, "probabilidad_deslizamiento": 0.6573, "nivel_riesgo": "Alto", "timestamp": "2026-05-20T04:05:55.914632+00:00"}, {"hybas_id": 6100090030, "probabilidad_deslizamiento": 0.8703, "nivel_riesgo": "Alto", "timestamp": "2026-05-20T04:05:55.914632+00:00"}, {"hybas_id": 6100090040, "probabilidad_deslizamiento": 0.8408, "nivel_riesgo": "Alto", "timestamp": "2026-05-20T04:05:55.914632+00:00"}, {"hybas_id": 6100089350, "probabilidad_deslizamiento": 0.8677, "nivel_riesgo": "Alto", "timestamp": "2026-05-20T04:05:55.914632+00:00"}, {"hybas_id": 6100991490, "probabilidad_deslizamiento": 0.0208, "nivel_riesgo": "Bajo", "timestamp": "2026-05-20T04:05:55.914632+00:00"}, {"hybas_id": 6100089360, "probabilidad_deslizamiento": 0.6775, "nivel_riesgo": "Alto", "timestamp": "2026-05-20T04:05:55.914632+00:00"}, {"hybas_id": 6100991110, "probabilidad_deslizamiento": 0.658, "nivel_riesgo": "Alto", "timestamp": "2026-05-20T04:05:55.914632+00:00"}, {"hybas_id": 6100088760, "probabilidad_deslizamiento": 0.6809, "nivel_riesgo": "Alto", "timestamp": "2026-05-20T04:05:55.914632+00:00"}, {"hybas_id": 6100086830, "probabilidad_deslizamiento": 0.6839, "nivel_riesgo": "Alto", "timestamp": "2026-05-20T04:05:55.914632+00:00"}, {"hybas_id": 6100086960, "probabilidad_deslizamiento": 0.6762, "nivel_riesgo": "Alto", "timestamp": "2026-05-20T04:05:55.914632+00:00"}, {"hybas_id": 6100086670, "probabilidad_deslizamiento": 0.6694, "nivel_riesgo": "Alto", "timestamp": "2026-05-20T04:05:55.914632+00:00"}, {"hybas_id": 6100992080, "probabilidad_deslizamiento": 0.6745, "nivel_riesgo": "Alto", "timestamp": "2026-05-20T04:05:55.914632+00:00"}, {"hybas_id": 6100992470, "probabilidad_deslizamiento": 0.0217, "nivel_riesgo": "Bajo", "timestamp": "2026-05-20T04:05:55.914632+00:00"}, {"hybas_id": 6100991500, "probabilidad_deslizamiento": 0.6739, "nivel_riesgo": "Alto", "timestamp": "2026-05-20T04:05:55.914632+00:00"}, {"hybas_id": 6100090480, "probabilidad_deslizamiento": 0.6453, "nivel_riesgo": "Alto", "timestamp": "2026-05-20T04:05:55.914632+00:00"}, {"hybas_id": 6100090460, "probabilidad_deslizamiento": 0.6752, "nivel_riesgo": "Alto", "timestamp": "2026-05-20T04:05:55.914632+00:00"}, {"hybas_id": 6100991170, "probabilidad_deslizamiento": 0.6739, "nivel_riesgo": "Alto", "timestamp": "2026-05-20T04:05:55.914632+00:00"}, {"hybas_id": 6100990790, "probabilidad_deslizamiento": 0.8418, "nivel_riesgo": "Alto", "timestamp": "2026-05-20T04:05:55.914632+00:00"}, {"hybas_id": 6100086970, "probabilidad_deslizamiento": 0.6831, "nivel_riesgo": "Alto", "timestamp": "2026-05-20T04:05:55.914632+00:00"}, {"hybas_id": 6100087110, "probabilidad_deslizamiento": 0.864, "nivel_riesgo": "Alto", "timestamp": "2026-05-20T04:05:55.914632+00:00"}, {"hybas_id": 6100086680, "probabilidad_deslizamiento": 0.6843, "nivel_riesgo": "Alto", "timestamp": "2026-05-20T04:05:55.914632+00:00"}, {"hybas_id": 6100087160, "probabilidad_deslizamiento": 0.8768, "nivel_riesgo": "Alto", "timestamp": "2026-05-20T04:05:55.914632+00:00"}, {"hybas_id": 6100086820, "probabilidad_deslizamiento": 0.8356, "nivel_riesgo": "Alto", "timestamp": "2026-05-20T04:05:55.914632+00:00"}, {"hybas_id": 6100087520, "probabilidad_deslizamiento": 0.6848, "nivel_riesgo": "Alto", "timestamp": "2026-05-20T04:05:55.914632+00:00"}, {"hybas_id": 6100087070, "probabilidad_deslizamiento": 0.0207, "nivel_riesgo": "Bajo", "timestamp": "2026-05-20T04:05:55.914632+00:00"}, {"hybas_id": 6100989400, "probabilidad_deslizamiento": 0.6594, "nivel_riesgo": "Alto", "timestamp": "2026-05-20T04:05:55.914632+00:00"}, {"hybas_id": 6100989520, "probabilidad_deslizamiento": 0.021, "nivel_riesgo": "Bajo", "timestamp": "2026-05-20T04:05:55.914632+00:00"}, {"hybas_id": 6100083200, "probabilidad_deslizamiento": 0.5876, "nivel_riesgo": "Medio", "timestamp": "2026-05-20T04:05:55.914632+00:00"}, {"hybas_id": 6100988830, "probabilidad_deslizamiento": 0.022, "nivel_riesgo": "Bajo", "timestamp": "2026-05-20T04:05:55.914632+00:00"}, {"hybas_id": 6100988780, "probabilidad_deslizamiento": 0.6586, "nivel_riesgo": "Alto", "timestamp": "2026-05-20T04:05:55.914632+00:00"}, {"hybas_id": 6100988520, "probabilidad_deslizamiento": 0.6754, "nivel_riesgo": "Alto", "timestamp": "2026-05-20T04:05:55.914632+00:00"}, {"hybas_id": 6100087830, "probabilidad_deslizamiento": 0.0215, "nivel_riesgo": "Bajo", "timestamp": "2026-05-20T04:05:55.914632+00:00"}, {"hybas_id": 6100085520, "probabilidad_deslizamiento": 0.8748, "nivel_riesgo": "Alto", "timestamp": "2026-05-20T04:05:55.914632+00:00"}, {"hybas_id": 6100990030, "probabilidad_deslizamiento": 0.6793, "nivel_riesgo": "Alto", "timestamp": "2026-05-20T04:05:55.914632+00:00"}, {"hybas_id": 6100085510, "probabilidad_deslizamiento": 0.8667, "nivel_riesgo": "Alto", "timestamp": "2026-05-20T04:05:55.914632+00:00"}, {"hybas_id": 6100084330, "probabilidad_deslizamiento": 0.8698, "nivel_riesgo": "Alto", "timestamp": "2026-05-20T04:05:55.914632+00:00"}, {"hybas_id": 6100085290, "probabilidad_deslizamiento": 0.6844, "nivel_riesgo": "Alto", "timestamp": "2026-05-20T04:05:55.914632+00:00"}, {"hybas_id": 6100085120, "probabilidad_deslizamiento": 0.6789, "nivel_riesgo": "Alto", "timestamp": "2026-05-20T04:05:55.914632+00:00"}, {"hybas_id": 6100084320, "probabilidad_deslizamiento": 0.6819, "nivel_riesgo": "Alto", "timestamp": "2026-05-20T04:05:55.914632+00:00"}, {"hybas_id": 6100988890, "probabilidad_deslizamiento": 0.0217, "nivel_riesgo": "Bajo", "timestamp": "2026-05-20T04:05:55.914632+00:00"}, {"hybas_id": 6100988510, "probabilidad_deslizamiento": 0.6599, "nivel_riesgo": "Alto", "timestamp": "2026-05-20T04:05:55.914632+00:00"}, {"hybas_id": 6100990130, "probabilidad_deslizamiento": 0.6838, "nivel_riesgo": "Alto", "timestamp": "2026-05-20T04:05:55.914632+00:00"}, {"hybas_id": 6100084880, "probabilidad_deslizamiento": 0.6838, "nivel_riesgo": "Alto", "timestamp": "2026-05-20T04:05:55.914632+00:00"}, {"hybas_id": 6100084980, "probabilidad_deslizamiento": 0.6843, "nivel_riesgo": "Alto", "timestamp": "2026-05-20T04:05:55.914632+00:00"}, {"hybas_id": 6100084440, "probabilidad_deslizamiento": 0.2537, "nivel_riesgo": "Bajo", "timestamp": "2026-05-20T04:05:55.914632+00:00"}, {"hybas_id": 6100084500, "probabilidad_deslizamiento": 0.6864, "nivel_riesgo": "Alto", "timestamp": "2026-05-20T04:05:55.914632+00:00"}, {"hybas_id": 6100083760, "probabilidad_deslizamiento": 0.6765, "nivel_riesgo": "Alto", "timestamp": "2026-05-20T04:05:55.914632+00:00"}, {"hybas_id": 6100083310, "probabilidad_deslizamiento": 0.658, "nivel_riesgo": "Alto", "timestamp": "2026-05-20T04:05:55.914632+00:00"}, {"hybas_id": 6100083850, "probabilidad_deslizamiento": 0.6864, "nivel_riesgo": "Alto", "timestamp": "2026-05-20T04:05:55.914632+00:00"}, {"hybas_id": 6100989030, "probabilidad_deslizamiento": 0.6747, "nivel_riesgo": "Alto", "timestamp": "2026-05-20T04:05:55.914632+00:00"}, {"hybas_id": 6100083370, "probabilidad_deslizamiento": 0.6864, "nivel_riesgo": "Alto", "timestamp": "2026-05-20T04:05:55.914632+00:00"}, {"hybas_id": 6100083040, "probabilidad_deslizamiento": 0.6827, "nivel_riesgo": "Alto", "timestamp": "2026-05-20T04:05:55.914632+00:00"}, {"hybas_id": 6100988360, "probabilidad_deslizamiento": 0.6767, "nivel_riesgo": "Alto", "timestamp": "2026-05-20T04:05:55.914632+00:00"}, {"hybas_id": 6100080220, "probabilidad_deslizamiento": 0.0213, "nivel_riesgo": "Bajo", "timestamp": "2026-05-20T04:05:55.914632+00:00"}, {"hybas_id": 6100987990, "probabilidad_deslizamiento": 0.6767, "nivel_riesgo": "Alto", "timestamp": "2026-05-20T04:05:55.914632+00:00"}, {"hybas_id": 6100079330, "probabilidad_deslizamiento": 0.0213, "nivel_riesgo": "Bajo", "timestamp": "2026-05-20T04:05:55.914632+00:00"}, {"hybas_id": 6100080060, "probabilidad_deslizamiento": 0.6772, "nivel_riesgo": "Alto", "timestamp": "2026-05-20T04:05:55.914632+00:00"}, {"hybas_id": 6100083210, "probabilidad_deslizamiento": 0.6783, "nivel_riesgo": "Alto", "timestamp": "2026-05-20T04:05:55.914632+00:00"}, {"hybas_id": 6100083380, "probabilidad_deslizamiento": 0.6798, "nivel_riesgo": "Alto", "timestamp": "2026-05-20T04:05:55.914632+00:00"}, {"hybas_id": 6100081370, "probabilidad_deslizamiento": 0.677, "nivel_riesgo": "Alto", "timestamp": "2026-05-20T04:05:55.914632+00:00"}, {"hybas_id": 6100988660, "probabilidad_deslizamiento": 0.6845, "nivel_riesgo": "Alto", "timestamp": "2026-05-20T04:05:55.914632+00:00"}, {"hybas_id": 6100988130, "probabilidad_deslizamiento": 0.6845, "nivel_riesgo": "Alto", "timestamp": "2026-05-20T04:05:55.914632+00:00"}, {"hybas_id": 6100080340, "probabilidad_deslizamiento": 0.8753, "nivel_riesgo": "Alto", "timestamp": "2026-05-20T04:05:55.914632+00:00"}, {"hybas_id": 6100080350, "probabilidad_deslizamiento": 0.6846, "nivel_riesgo": "Alto", "timestamp": "2026-05-20T04:05:55.914632+00:00"}, {"hybas_id": 6100079930, "probabilidad_deslizamiento": 0.0224, "nivel_riesgo": "Bajo", "timestamp": "2026-05-20T04:05:55.914632+00:00"}, {"hybas_id": 6100080070, "probabilidad_deslizamiento": 0.6864, "nivel_riesgo": "Alto", "timestamp": "2026-05-20T04:05:55.914632+00:00"}, {"hybas_id": 6100078380, "probabilidad_deslizamiento": 0.6846, "nivel_riesgo": "Alto", "timestamp": "2026-05-20T04:05:55.914632+00:00"}, {"hybas_id": 6100988210, "probabilidad_deslizamiento": 0.6819, "nivel_riesgo": "Alto", "timestamp": "2026-05-20T04:05:55.914632+00:00"}, {"hybas_id": 6100081300, "probabilidad_deslizamiento": 0.8609, "nivel_riesgo": "Alto", "timestamp": "2026-05-20T04:05:55.914632+00:00"}, {"hybas_id": 6100080190, "probabilidad_deslizamiento": 0.6832, "nivel_riesgo": "Alto", "timestamp": "2026-05-20T04:05:55.914632+00:00"}, {"hybas_id": 6100987350, "probabilidad_deslizamiento": 0.6826, "nivel_riesgo": "Alto", "timestamp": "2026-05-20T04:05:55.914632+00:00"}, {"hybas_id": 6100987310, "probabilidad_deslizamiento": 0.6826, "nivel_riesgo": "Alto", "timestamp": "2026-05-20T04:05:55.914632+00:00"}, {"hybas_id": 6100987280, "probabilidad_deslizamiento": 0.6826, "nivel_riesgo": "Alto", "timestamp": "2026-05-20T04:05:55.914632+00:00"}, {"hybas_id": 6100987210, "probabilidad_deslizamiento": 0.6826, "nivel_riesgo": "Alto", "timestamp": "2026-05-20T04:05:55.914632+00:00"}, {"hybas_id": 6100076200, "probabilidad_deslizamiento": 0.8722, "nivel_riesgo": "Alto", "timestamp": "2026-05-20T04:05:55.914632+00:00"}, {"hybas_id": 6100076190, "probabilidad_deslizamiento": 0.0195, "nivel_riesgo": "Bajo", "timestamp": "2026-05-20T04:05:55.914632+00:00"}, {"hybas_id": 6100075650, "probabilidad_deslizamiento": 0.8708, "nivel_riesgo": "Alto", "timestamp": "2026-05-20T04:05:55.914632+00:00"}, {"hybas_id": 6100079340, "probabilidad_deslizamiento": 0.73, "nivel_riesgo": "Alto", "timestamp": "2026-05-20T04:05:55.914632+00:00"}, {"hybas_id": 6100078390, "probabilidad_deslizamiento": 0.0221, "nivel_riesgo": "Bajo", "timestamp": "2026-05-20T04:05:55.914632+00:00"}, {"hybas_id": 6100078620, "probabilidad_deslizamiento": 0.6773, "nivel_riesgo": "Alto", "timestamp": "2026-05-20T04:05:55.914632+00:00"}, {"hybas_id": 6100076590, "probabilidad_deslizamiento": 0.8766, "nivel_riesgo": "Alto", "timestamp": "2026-05-20T04:05:55.914632+00:00"}, {"hybas_id": 6100078150, "probabilidad_deslizamiento": 0.6831, "nivel_riesgo": "Alto", "timestamp": "2026-05-20T04:05:55.914632+00:00"}, {"hybas_id": 6100078120, "probabilidad_deslizamiento": 0.6853, "nivel_riesgo": "Alto", "timestamp": "2026-05-20T04:05:55.914632+00:00"}, {"hybas_id": 6100077380, "probabilidad_deslizamiento": 0.6831, "nivel_riesgo": "Alto", "timestamp": "2026-05-20T04:05:55.914632+00:00"}, {"hybas_id": 6100077300, "probabilidad_deslizamiento": 0.0217, "nivel_riesgo": "Bajo", "timestamp": "2026-05-20T04:05:55.914632+00:00"}, {"hybas_id": 6100075880, "probabilidad_deslizamiento": 0.0213, "nivel_riesgo": "Bajo", "timestamp": "2026-05-20T04:05:55.914632+00:00"}], "alto_riesgo": [6100104690, 6100997810, 6100102970, 6100101980, 6100101810, 6100101900, 6100104620, 6100101610, 6100099730, 6100098850, 6100097280, 6100097200, 6100101820, 6100100130, 6100099820, 6100099720, 6100099410, 6100099180, 6100097540, 6100115670, 6100113400, 6100110930, 6100107990, 6101002540, 6100113590, 6101001740, 6100108370, 6101001140, 6101000660, 6100108150, 6100108540, 6100108440, 6100107870, 6100107440, 6100107720, 6100107450, 6100106660, 6100105430, 6100999210, 6100107550, 6100104630, 6100106470, 6100106510, 6100999670, 6100105920, 6100105420, 6100105890, 6100104700, 6100108000, 6100105440, 6100102520, 6100102870, 6100997110, 6100103540, 6100101920, 6100101460, 6100101910, 6100101450, 6100101500, 6100100410, 6100996830, 6100099740, 6100103490, 6100997340, 6100997000, 6100996770, 6100996620, 6100098450, 6100098110, 6100099560, 6100098530, 6100099640, 6100098050, 6100097360, 6100994380, 6100098160, 6100098100, 6100097950, 6100995750, 6100096590, 6100995040, 6100095120, 6100097270, 6100096440, 6100096470, 6100096580, 6100098370, 6100097170, 6100097210, 6100097150, 6100096290, 6100097140, 6100096230, 6100093290, 6100097050, 6100097490, 6100093560, 6100093480, 6100091910, 6100091540, 6100992160, 6100094710, 6100092610, 6100092620, 6100092570, 6100092360, 6100091200, 6100992860, 6100091210, 6100092270, 6100089880, 6100089420, 6100088150, 6100088100, 6100991090, 6100990970, 6100086490, 6100088160, 6100989940, 6100989930, 6100988770, 6100098060, 6100994400, 6100993900, 6100092760, 6100092590, 6100092750, 6100092580, 6100092020, 6100094190, 6100094200, 6100093490, 6100093300, 6100093380, 6100091600, 6100092160, 6100091470, 6100094020, 6100993480, 6100092250, 6100992880, 6100091060, 6100091310, 6100090450, 6100091020, 6100089760, 6100992380, 6100089730, 6100089110, 6100089040, 6100089080, 6100088710, 6100087940, 6100090370, 6100089700, 6100089710, 6100086420, 6100086270, 6100991260, 6100991100, 6100990720, 6100990330, 6100990390, 6100990400, 6100080810, 6100986590, 6100077630, 6100076110, 6100985410, 6100075620, 6100985390, 6100073970, 6100987200, 6100989980, 6100085550, 6100082590, 6100083190, 6100082500, 6100081230, 6100083820, 6100988420, 6100081290, 6100000220, 6100081280, 6100987560, 6100078040, 6100000200, 6100988120, 6100081180, 6100080650, 6100080740, 6100000240, 6100079080, 6100000260, 6100000170, 6100075200, 6100074340, 6100000310, 6100073780, 6100984480, 6100072300, 6100984100, 6100071840, 6100000360, 6100000340, 6100000350, 6100985430, 6100072660, 6100000380, 6100107350, 6100106480, 6100105730, 6100105250, 6100104150, 6100103680, 6100102980, 6100102530, 6100102120, 6100102080, 6100101420, 6100100810, 6100098640, 6100101560, 6100100530, 6100099660, 6100100740, 6100098590, 6100097870, 6100096110, 6100097100, 6100097070, 6100096480, 6100095830, 6100095550, 6100095800, 6100111070, 6100110470, 6100109040, 6100108550, 6100108450, 6100109050, 6100108860, 6100106010, 6100105770, 6100105540, 6100105720, 6100998540, 6100105450, 6100107280, 6100106280, 6100104840, 6100104850, 6100104710, 6100104080, 6100102390, 6100104210, 6100104400, 6100104140, 6100101520, 6100101130, 6100996840, 6100101410, 6100101550, 6100102230, 6100101620, 6100101530, 6100996730, 6100996560, 6100099570, 6100096990, 6100997020, 6100996360, 6100099190, 6100098170, 6100097500, 6100995470, 6100097460, 6100996300, 6100996230, 6100996250, 6100995660, 6100995020, 6100994540, 6100994210, 6100094210, 6100096180, 6100096640, 6100095020, 6100094940, 6100094960, 6100094080, 6100093010, 6100092910, 6100094950, 6100994410, 6100094230, 6100092180, 6100993300, 6100090820, 6100092090, 6100092100, 6100095870, 6100096940, 6100095790, 6100095880, 6100993810, 6100993510, 6100993400, 6100993190, 6100992220, 6100092480, 6100091400, 6100091040, 6100090980, 6100090640, 6100089740, 6100088820, 6100091230, 6100090900, 6100091690, 6100090750, 6100091160, 6100090680, 6100090810, 6100087980, 6100087080, 6100990150, 6100989320, 6100083220, 6100988690, 6100094220, 6100092300, 6100091070, 6100992360, 6100089120, 6100088650, 6100087570, 6100090030, 6100090040, 6100089350, 6100089360, 6100991110, 6100088760, 6100086830, 6100086960, 6100086670, 6100992080, 6100991500, 6100090480, 6100090460, 6100991170, 6100990790, 6100086970, 6100087110, 6100086680, 6100087160, 6100086820, 6100087520, 6100989400, 6100988780, 6100988520, 6100085520, 6100990030, 6100085510, 6100084330, 6100085290, 6100085120, 6100084320, 6100988510, 6100990130, 6100084880, 6100084980, 6100084500, 6100083760, 6100083310, 6100083850, 6100989030, 6100083370, 6100083040, 6100988360, 6100987990, 6100080060, 6100083210, 6100083380, 6100081370, 6100988660, 6100988130, 6100080340, 6100080350, 6100080070, 6100078380, 6100988210, 6100081300, 6100080190, 6100987350, 6100987310, 6100987280, 6100987210, 6100076200, 6100075650, 6100079340, 6100078620, 6100076590, 6100078150, 6100078120, 6100077380], "resumen": {"alto": 406, "medio": 4, "bajo": 139}, "generado_utc": "2026-05-20T04:05:55.914632+00:00", "features_usadas": ["precip_acum_14d", "precip_max_diario_14d", "precip_dias_lluvia_14d", "precip_acum_7d", "precip_acum_3d", "SUB_AREA", "UP_AREA", "DIST_MAIN", "ORDER", "semana_sin", "semana_cos", "mes_sin", "mes_cos", "soil_moisture_14d"]}